{"Top": "20101220233002", "Filename": "2010-12-20_2330_US_KCAL_Inside_Edition"}
{"Collection": "Communication Studies Archive, UCLA"}
{"UID": "336f2a28-0c95-11e0-8dea-001517add6fa"}
{"Duration": "0:29:28.70"}
{"Video_Picture_Size": "640x368", "Original_Picture_Size": ""}
{"Comment": ""}
{"Language": "ENG"}
{"Local_Broadcast_Time": "2010-12-20 15:30 America/Los_Angeles"}
{"Annotation_Tag": "SEG_01", "Creation_Time": "2014-02-03 01:06:44", "Source_Program": "commercial_detection.py", "Source_Person": "Weixin Li"}
{"StartTime": "20101220233005.000", "EndTime": "20101220235930.000", "PrimaryTag": "SEG", "Type": "Story"}
{"StartTime": "20101220233005.000", "EndTime": "20101220233008.000", "PrimaryTag": "CC1", "Text": "PUBLIC APPEARANCE SINCE GETTING "}
{"StartTime": "20101220233008.000", "EndTime": "20101220233009.000", "PrimaryTag": "CC1", "Text": "ENGAGED.                        "}
{"StartTime": "20101220233009.000", "EndTime": "20101220233009.000", "PrimaryTag": "CC1", "Text": "PLUS, JUST REVEALED.            "}
{"StartTime": "20101220233009.000", "EndTime": "20101220233015.000", "PrimaryTag": "CC1", "Text": "HOW BERNARD MADOFF REACTED TO   "}
{"StartTime": "20101220233015.000", "EndTime": "20101220233017.000", "PrimaryTag": "CC1", "Text": "HIS SON'S SUICIDE.              "}
{"StartTime": "20101220233017.000", "EndTime": "20101220233022.000", "PrimaryTag": "CC1", "Text": ">> HE BREAKS DOWN REFUSING TO   "}
{"StartTime": "20101220233022.000", "EndTime": "20101220233022.000", "PrimaryTag": "CC1", "Text": "EAT FOR DAYS.                   "}
{"StartTime": "20101220233022.000", "EndTime": "20101220233025.000", "PrimaryTag": "CC1", "Text": ">> COULD THESE WOMEN BE VICTIMS "}
{"StartTime": "20101220233025.000", "EndTime": "20101220233027.000", "PrimaryTag": "CC1", "Text": "OF THE GRIM SLEEPER.            "}
{"StartTime": "20101220233027.000", "EndTime": "20101220233028.000", "PrimaryTag": "CC1", "Text": "180 PHOTOS FOUND IN HIS HOME.   "}
{"StartTime": "20101220233028.000", "EndTime": "20101220233034.000", "PrimaryTag": "CC1", "Text": "WHO ARE THEY AND WHY DO SO MANY "}
{"StartTime": "20101220233034.000", "EndTime": "20101220233035.000", "PrimaryTag": "CC1", "Text": "SEEM TO BE SLEEPING.            "}
{"StartTime": "20101220233035.000", "EndTime": "20101220233037.000", "PrimaryTag": "CC1", "Text": "AND KATE HOLMES' BIRTHDAY       "}
{"StartTime": "20101220233037.000", "EndTime": "20101220233039.000", "PrimaryTag": "CC1", "Text": "SMOOCH AND CAMERON DIAZ POOL    "}
{"StartTime": "20101220233039.000", "EndTime": "20101220233040.000", "PrimaryTag": "CC1", "Text": "SIDE WITH ALEX RODRIGUEZ'S      "}
{"StartTime": "20101220233040.000", "EndTime": "20101220233040.000", "PrimaryTag": "CC1", "Text": "KIDS.                           "}
{"StartTime": "20101220233040.000", "EndTime": "20101220233047.000", "PrimaryTag": "CC1", "Text": "PLUS RED CARPET MOMENTS OF THE  "}
{"StartTime": "20101220233047.000", "EndTime": "20101220233047.000", "PrimaryTag": "CC1", "Text": "YEAR.                           "}
{"StartTime": "20101220233047.000", "EndTime": "20101220233054.000", "PrimaryTag": "CC1", "Text": "WHO SHINED IN 2010.             "}
{"StartTime": "20101220233054.000", "EndTime": "20101220233055.000", "PrimaryTag": "CC1", "Text": "NOW, INSIDE EDITION WITH        "}
{"StartTime": "20101220233055.000", "EndTime": "20101220233055.000", "PrimaryTag": "CC1", "Text": "DEBORAH NORVILLE.               "}
{"StartTime": "20101220233055.000", "EndTime": "20101220233057.000", "PrimaryTag": "CC1", "Text": ">> IT HAS BEEN MORE THAN A WEEK "}
{"StartTime": "20101220233057.000", "EndTime": "20101220233059.000", "PrimaryTag": "CC1", "Text": "SINCE A LAS VEGAS SHOW GIRL     "}
{"StartTime": "20101220233059.000", "EndTime": "20101220233102.000", "PrimaryTag": "CC1", "Text": "DIDN'T SHOW UP FOR WORK.        "}
{"StartTime": "20101220233102.000", "EndTime": "20101220233103.000", "PrimaryTag": "CC1", "Text": "HER CAR WAS FOUND ABANDONED BUT "}
{"StartTime": "20101220233103.000", "EndTime": "20101220233106.000", "PrimaryTag": "CC1", "Text": "NO SIGN OF THE WOMAN WHOSE LIFE "}
{"StartTime": "20101220233106.000", "EndTime": "20101220233107.000", "PrimaryTag": "CC1", "Text": "WAS TO BE A DANCER.             "}
{"StartTime": "20101220233107.000", "EndTime": "20101220233108.000", "PrimaryTag": "CC1", "Text": "PAUL BOYD HAS THE STORY.        "}
{"StartTime": "20101220233108.000", "EndTime": "20101220233110.000", "PrimaryTag": "CC1", "Text": ">>  Randy: A SEXY SHOW GIRL AND "}
{"StartTime": "20101220233110.000", "EndTime": "20101220233113.000", "PrimaryTag": "CC1", "Text": "TOPLESS MODEL NOW SHE IS        "}
{"StartTime": "20101220233113.000", "EndTime": "20101220233121.000", "PrimaryTag": "CC1", "Text": "MISSING AND THE FOCUS OF AN     "}
{"StartTime": "20101220233121.000", "EndTime": "20101220233122.000", "PrimaryTag": "CC1", "Text": "INCREASING SEARCH.              "}
{"StartTime": "20101220233122.000", "EndTime": "20101220233124.000", "PrimaryTag": "CC1", "Text": "SHE WORKS IN THE LUXOR HOTEL ON "}
{"StartTime": "20101220233124.000", "EndTime": "20101220233126.000", "PrimaryTag": "CC1", "Text": "THE LAS VEGAS STRIP AND ALSO A  "}
{"StartTime": "20101220233126.000", "EndTime": "20101220233129.000", "PrimaryTag": "CC1", "Text": "DANCER AT THE PALMS.            "}
{"StartTime": "20101220233129.000", "EndTime": "20101220233131.000", "PrimaryTag": "CC1", "Text": "POLICE SAY SHE HASN'T BEEN SEEN "}
{"StartTime": "20101220233131.000", "EndTime": "20101220233132.000", "PrimaryTag": "CC1", "Text": "SINCE HER LAST PERFORMANCE OVER "}
{"StartTime": "20101220233132.000", "EndTime": "20101220233134.000", "PrimaryTag": "CC1", "Text": "A WEEK AGO WHEN SHE WENT TO     "}
{"StartTime": "20101220233134.000", "EndTime": "20101220233135.000", "PrimaryTag": "CC1", "Text": "VISIT HER EX-BOYFRIEND.         "}
{"StartTime": "20101220233135.000", "EndTime": "20101220233136.000", "PrimaryTag": "CC1", "Text": "WHEN SHE FAILED TO TURN UP FOR  "}
{"StartTime": "20101220233136.000", "EndTime": "20101220233138.000", "PrimaryTag": "CC1", "Text": "DANCE PRACTICE THE NEXT DAY     "}
{"StartTime": "20101220233138.000", "EndTime": "20101220233143.000", "PrimaryTag": "CC1", "Text": "FRIENDS RAISED THE ALARM.       "}
{"StartTime": "20101220233143.000", "EndTime": "20101220233144.000", "PrimaryTag": "CC1", "Text": "HER EX-BOYFRIEND SAID SHE       "}
{"StartTime": "20101220233144.000", "EndTime": "20101220233145.000", "PrimaryTag": "CC1", "Text": "VISITED HIM FOR A SHORT TIME    "}
{"StartTime": "20101220233145.000", "EndTime": "20101220233149.000", "PrimaryTag": "CC1", "Text": "AND LEFT TO SEE OTHER FRIENDS.  "}
{"StartTime": "20101220233149.000", "EndTime": "20101220233151.000", "PrimaryTag": "CC1", "Text": "A REPORT SAYS DEBBIE TEXTED HER "}
{"StartTime": "20101220233151.000", "EndTime": "20101220233153.000", "PrimaryTag": "CC1", "Text": "MOM JUST A WEEK BEFORE HER      "}
{"StartTime": "20101220233153.000", "EndTime": "20101220233155.000", "PrimaryTag": "CC1", "Text": "DISAPPEARANCE WRITING IN CASE   "}
{"StartTime": "20101220233155.000", "EndTime": "20101220233156.000", "PrimaryTag": "CC1", "Text": "THERE IS EVER AN EMERGENCY      "}
{"StartTime": "20101220233156.000", "EndTime": "20101220233158.000", "PrimaryTag": "CC1", "Text": "ABOUT ME CONTACT BLUE GRIFFITH  "}
{"StartTime": "20101220233158.000", "EndTime": "20101220233200.000", "PrimaryTag": "CC1", "Text": "IN VEGAS, MY EX-BOYFRIEND NOT   "}
{"StartTime": "20101220233200.000", "EndTime": "20101220233201.000", "PrimaryTag": "CC1", "Text": "MY BEST FRIEND.                 "}
{"StartTime": "20101220233201.000", "EndTime": "20101220233202.000", "PrimaryTag": "CC1", "Text": "THIS RAUNCHY MUSIC VIDEO SHE    "}
{"StartTime": "20101220233202.000", "EndTime": "20101220233204.000", "PrimaryTag": "CC1", "Text": "MADE WITH HIM WHEN THEY WERE    "}
{"StartTime": "20101220233204.000", "EndTime": "20101220233206.000", "PrimaryTag": "CC1", "Text": "DATING IS ON HER YOUTUBE        "}
{"StartTime": "20101220233206.000", "EndTime": "20101220233206.000", "PrimaryTag": "CC1", "Text": "CHANNEL.                        "}
{"StartTime": "20101220233206.000", "EndTime": "20101220233209.000", "PrimaryTag": "CC1", "Text": "THERE ARE ALSO INDICATIONS SHE  "}
{"StartTime": "20101220233209.000", "EndTime": "20101220233209.000", "PrimaryTag": "CC1", "Text": "WAS BEING STALKED.              "}
{"StartTime": "20101220233209.000", "EndTime": "20101220233212.000", "PrimaryTag": "CC1", "Text": "ON HER MYSPACE STAGE SHE SAYS   "}
{"StartTime": "20101220233212.000", "EndTime": "20101220233213.000", "PrimaryTag": "CC1", "Text": "SHE DANCES IN VEGAS SHOWS BUT   "}
{"StartTime": "20101220233213.000", "EndTime": "20101220233218.000", "PrimaryTag": "CC1", "Text": "CAN'T SAY WHICH ONE, TOO MANY   "}
{"StartTime": "20101220233218.000", "EndTime": "20101220233218.000", "PrimaryTag": "CC1", "Text": "STALKERS.                       "}
{"StartTime": "20101220233218.000", "EndTime": "20101220233219.000", "PrimaryTag": "CC1", "Text": "DEBBIE'S PRISM CAR WAS FOUND    "}
{"StartTime": "20101220233219.000", "EndTime": "20101220233222.000", "PrimaryTag": "CC1", "Text": "ABANDONED NEXT WEEK BUT WITH NO "}
{"StartTime": "20101220233222.000", "EndTime": "20101220233224.000", "PrimaryTag": "CC1", "Text": "SIGN OF DEBBIE.                 "}
{"StartTime": "20101220233224.000", "EndTime": "20101220233225.000", "PrimaryTag": "CC1", "Text": "PHOTOGRAPHER JASON LITTLE IS A  "}
{"StartTime": "20101220233225.000", "EndTime": "20101220233226.000", "PrimaryTag": "CC1", "Text": "CLOSE FRIEND.                   "}
{"StartTime": "20101220233226.000", "EndTime": "20101220233230.000", "PrimaryTag": "CC1", "Text": ">> WHAT DO YOU THINK HAS        "}
{"StartTime": "20101220233230.000", "EndTime": "20101220233230.000", "PrimaryTag": "CC1", "Text": "HAPPENED HERE?                  "}
{"StartTime": "20101220233230.000", "EndTime": "20101220233232.000", "PrimaryTag": "CC1", "Text": ">> I WOULD SAY FOUL PLAY.       "}
{"StartTime": "20101220233232.000", "EndTime": "20101220233233.000", "PrimaryTag": "CC1", "Text": ">> DEBBIE HAS AN IMPRESSIVE     "}
{"StartTime": "20101220233233.000", "EndTime": "20101220233235.000", "PrimaryTag": "CC1", "Text": "RESUME WITH BOTH A LAW DEGREE   "}
{"StartTime": "20101220233235.000", "EndTime": "20101220233236.000", "PrimaryTag": "CC1", "Text": "AND MBA BUT INSTEAD OF A CAREER "}
{"StartTime": "20101220233236.000", "EndTime": "20101220233239.000", "PrimaryTag": "CC1", "Text": "IN LAW OR WALL STREET SHE       "}
{"StartTime": "20101220233239.000", "EndTime": "20101220233241.000", "PrimaryTag": "CC1", "Text": "BECAME A WASHINGTON REDSKINS    "}
{"StartTime": "20101220233241.000", "EndTime": "20101220233242.000", "PrimaryTag": "CC1", "Text": "CHEERLEADERRER IN 2007.         "}
{"StartTime": "20101220233242.000", "EndTime": "20101220233244.000", "PrimaryTag": "CC1", "Text": "SHE LEFT THE REDSKINS TO FOLLOW "}
{"StartTime": "20101220233244.000", "EndTime": "20101220233246.000", "PrimaryTag": "CC1", "Text": "ANOTHER DREAM AS A DANCER AND   "}
{"StartTime": "20101220233246.000", "EndTime": "20101220233246.000", "PrimaryTag": "CC1", "Text": "MODEL.                          "}
{"StartTime": "20101220233246.000", "EndTime": "20101220233249.000", "PrimaryTag": "CC1", "Text": "ON HER FACEBOOK PAGE SHE WRITES "}
{"StartTime": "20101220233249.000", "EndTime": "20101220233253.000", "PrimaryTag": "CC1", "Text": "LIVE LIFE TO THE FULLEST.      \n20101220233253.000|20101220233254.000|CC1|LIFE IS SHORT.                  \n20101220233254.000|20101220233256.000|CC1|DEATH IS FOREVER.              "}
{"StartTime": "20101220233256.000", "EndTime": "20101220233257.000", "PrimaryTag": "CC1", "Text": ">> WHEN POLICE FOUND DEBBIE'S   "}
{"StartTime": "20101220233257.000", "EndTime": "20101220233258.000", "PrimaryTag": "CC1", "Text": "CAR HER PURSE WAS ON THE BACK   "}
{"StartTime": "20101220233258.000", "EndTime": "20101220233303.000", "PrimaryTag": "CC1", "Text": "SEAT WITH HER MAKEUP AND        "}
{"StartTime": "20101220233303.000", "EndTime": "20101220233304.000", "PrimaryTag": "CC1", "Text": "LICENSE PLATES HAD BEEN         "}
{"StartTime": "20101220233304.000", "EndTime": "20101220233304.000", "PrimaryTag": "CC1", "Text": "REMOVED.                        "}
{"StartTime": "20101220233304.000", "EndTime": "20101220233305.000", "PrimaryTag": "CC1", "Text": "WINTER OFFICIALLY BEGINS        "}
{"StartTime": "20101220233305.000", "EndTime": "20101220233310.000", "PrimaryTag": "CC1", "Text": "TOMORROW ACCORDING TO THE       "}
{"StartTime": "20101220233310.000", "EndTime": "20101220233311.000", "PrimaryTag": "CC1", "Text": "CALENDAR BUT ACCORDING TO THE   "}
{"StartTime": "20101220233311.000", "EndTime": "20101220233315.000", "PrimaryTag": "CC1", "Text": "WEATHER CHANCES ARE YOU WILL    "}
{"StartTime": "20101220233315.000", "EndTime": "20101220233315.000", "PrimaryTag": "CC1", "Text": "GET CHAOS.                      "}
{"StartTime": "20101220233315.000", "EndTime": "20101220233318.000", "PrimaryTag": "CC1", "Text": ">> A SLIP AND SLIDE NIGHTMARE   "}
{"StartTime": "20101220233318.000", "EndTime": "20101220233319.000", "PrimaryTag": "CC1", "Text": "CAUSING A CHAIN REACTION        "}
{"StartTime": "20101220233319.000", "EndTime": "20101220233320.000", "PrimaryTag": "CC1", "Text": "PILEUP.                         "}
{"StartTime": "20101220233320.000", "EndTime": "20101220233324.000", "PrimaryTag": "CC1", "Text": "IT STARTED AS THIS BLACK SUV    "}
{"StartTime": "20101220233324.000", "EndTime": "20101220233325.000", "PrimaryTag": "CC1", "Text": "AND A WHITE TRUCK SLID          "}
{"StartTime": "20101220233325.000", "EndTime": "20101220233328.000", "PrimaryTag": "CC1", "Text": "BACKWARDS DOWN A STEEP SNOW     "}
{"StartTime": "20101220233328.000", "EndTime": "20101220233330.000", "PrimaryTag": "CC1", "Text": "COVERED HILL IN SPOKANE,        "}
{"StartTime": "20101220233330.000", "EndTime": "20101220233330.000", "PrimaryTag": "CC1", "Text": "WASHINGTON.                     "}
{"StartTime": "20101220233330.000", "EndTime": "20101220233331.000", "PrimaryTag": "CC1", "Text": "BOTH VEHICLES TURN 180 DEGREES  "}
{"StartTime": "20101220233331.000", "EndTime": "20101220233332.000", "PrimaryTag": "CC1", "Text": "BUT THE SUV CAN'T STOP AND      "}
{"StartTime": "20101220233332.000", "EndTime": "20101220233334.000", "PrimaryTag": "CC1", "Text": "CRASHES INTO A PARKED CAR       "}
{"StartTime": "20101220233334.000", "EndTime": "20101220233336.000", "PrimaryTag": "CC1", "Text": "SETTING OFF A CHAIN REACTION.   "}
{"StartTime": "20101220233336.000", "EndTime": "20101220233338.000", "PrimaryTag": "CC1", "Text": "THEN THIS OUT OF CONTROL RED    "}
{"StartTime": "20101220233338.000", "EndTime": "20101220233340.000", "PrimaryTag": "CC1", "Text": "TRUCK SLIDES BACKWARDS DOWN THE "}
{"StartTime": "20101220233340.000", "EndTime": "20101220233342.000", "PrimaryTag": "CC1", "Text": "HILL AND PLOWS INTO EVERYBODY.  "}
{"StartTime": "20101220233342.000", "EndTime": "20101220233343.000", "PrimaryTag": "CC1", "Text": "A FEW SECONDS LATER THIS FAST   "}
{"StartTime": "20101220233343.000", "EndTime": "20101220233345.000", "PrimaryTag": "CC1", "Text": "MOVING CAR JUST MISSES A HEAD   "}
{"StartTime": "20101220233345.000", "EndTime": "20101220233346.000", "PrimaryTag": "CC1", "Text": "ON COLLISION BUT THE OUT OF     "}
{"StartTime": "20101220233346.000", "EndTime": "20101220233349.000", "PrimaryTag": "CC1", "Text": "CONTROL CAR STILL SLAMS INTO    "}
{"StartTime": "20101220233349.000", "EndTime": "20101220233350.000", "PrimaryTag": "CC1", "Text": "THE PILEUP.                     "}
{"StartTime": "20101220233350.000", "EndTime": "20101220233351.000", "PrimaryTag": "CC1", "Text": "FINALLY, LOOK AT THIS BLACK     "}
{"StartTime": "20101220233351.000", "EndTime": "20101220233352.000", "PrimaryTag": "CC1", "Text": "TRUCK.                          "}
{"StartTime": "20101220233352.000", "EndTime": "20101220233355.000", "PrimaryTag": "CC1", "Text": "IT SPINS OFF THE ROAD BUT CAN'T "}
{"StartTime": "20101220233355.000", "EndTime": "20101220233355.000", "PrimaryTag": "CC1", "Text": "STOP.                           "}
{"StartTime": "20101220233355.000", "EndTime": "20101220233400.000", "PrimaryTag": "CC1", "Text": ">> Reporter: THEY ARE GOING TO  "}
{"StartTime": "20101220233400.000", "EndTime": "20101220233402.000", "PrimaryTag": "CC1", "Text": "HIT STOP.                       "}
{"StartTime": "20101220233402.000", "EndTime": "20101220233403.000", "PrimaryTag": "CC1", "Text": ">> FORTUNATELY NOBODY WAS HURT. "}
{"StartTime": "20101220233403.000", "EndTime": "20101220233405.000", "PrimaryTag": "CC1", "Text": "NOW LOOK AT TERRIFYING DASH CAM "}
{"StartTime": "20101220233405.000", "EndTime": "20101220233406.000", "PrimaryTag": "CC1", "Text": "VIDEO AS AN OUT OF CONTROL      "}
{"StartTime": "20101220233406.000", "EndTime": "20101220233408.000", "PrimaryTag": "CC1", "Text": "TRUCK SLAMS INTO A POLICE CAR   "}
{"StartTime": "20101220233408.000", "EndTime": "20101220233411.000", "PrimaryTag": "CC1", "Text": "ON AN ICE COVERED HIGHWAY IN    "}
{"StartTime": "20101220233411.000", "EndTime": "20101220233411.000", "PrimaryTag": "CC1", "Text": "NEBRASKA.                       "}
{"StartTime": "20101220233411.000", "EndTime": "20101220233412.000", "PrimaryTag": "CC1", "Text": "THE COP WAS HELPING A STRANDED  "}
{"StartTime": "20101220233412.000", "EndTime": "20101220233414.000", "PrimaryTag": "CC1", "Text": "MOTORIST AND HAD TO RUN FOR HIS "}
{"StartTime": "20101220233414.000", "EndTime": "20101220233417.000", "PrimaryTag": "CC1", "Text": "LIFE AS THE STRUCK LOST CONTROL "}
{"StartTime": "20101220233417.000", "EndTime": "20101220233418.000", "PrimaryTag": "CC1", "Text": "AND CRASHED INTO THE POLICE     "}
{"StartTime": "20101220233418.000", "EndTime": "20101220233419.000", "PrimaryTag": "CC1", "Text": "CAR.                            "}
{"StartTime": "20101220233419.000", "EndTime": "20101220233422.000", "PrimaryTag": "CC1", "Text": "AND HERE IS HOME VIDEO OF A     "}
{"StartTime": "20101220233422.000", "EndTime": "20101220233424.000", "PrimaryTag": "CC1", "Text": "DRAMATIC RESCUE OF TWO DEER     "}
{"StartTime": "20101220233424.000", "EndTime": "20101220233426.000", "PrimaryTag": "CC1", "Text": "STRANDED ON THE ICE COVERED     "}
{"StartTime": "20101220233426.000", "EndTime": "20101220233427.000", "PrimaryTag": "CC1", "Text": "MISSISSIPPI RIVER.              "}
{"StartTime": "20101220233427.000", "EndTime": "20101220233428.000", "PrimaryTag": "CC1", "Text": "A HELICOPTER USING WIND POWER   "}
{"StartTime": "20101220233428.000", "EndTime": "20101220233431.000", "PrimaryTag": "CC1", "Text": "FROM ITS BLADE ACTUALLY MANAGED "}
{"StartTime": "20101220233431.000", "EndTime": "20101220233433.000", "PrimaryTag": "CC1", "Text": "TO PUSH ONE DEER TO THE SHORE.  "}
{"StartTime": "20101220233433.000", "EndTime": "20101220233436.000", "PrimaryTag": "CC1", "Text": "RESCUER USED SKIS TO REACH THE  "}
{"StartTime": "20101220233436.000", "EndTime": "20101220233438.000", "PrimaryTag": "CC1", "Text": "OTHER DEER WITH A TOW LINE AND  "}
{"StartTime": "20101220233438.000", "EndTime": "20101220233439.000", "PrimaryTag": "CC1", "Text": "JOINED ANOTHER GUY WHO WALKED   "}
{"StartTime": "20101220233439.000", "EndTime": "20101220233440.000", "PrimaryTag": "CC1", "Text": "OUT ON THE ICE.                 "}
{"StartTime": "20101220233440.000", "EndTime": "20101220233443.000", "PrimaryTag": "CC1", "Text": "THEY HOOK UP THE DEER TO A      "}
{"StartTime": "20101220233443.000", "EndTime": "20101220233445.000", "PrimaryTag": "CC1", "Text": "HARNESS AND OTHER RESCUERS THEN "}
{"StartTime": "20101220233445.000", "EndTime": "20101220233447.000", "PrimaryTag": "CC1", "Text": "PULLED THE ANIMAL ACROSS THE    "}
{"StartTime": "20101220233447.000", "EndTime": "20101220233447.000", "PrimaryTag": "CC1", "Text": "ICE TO SAFETY.                  "}
{"StartTime": "20101220233447.000", "EndTime": "20101220233449.000", "PrimaryTag": "CC1", "Text": ">> OVER IN BRITAIN THEY ARE     "}
{"StartTime": "20101220233449.000", "EndTime": "20101220233450.000", "PrimaryTag": "CC1", "Text": "SHOVELING OUT OF THE WORST      "}
{"StartTime": "20101220233450.000", "EndTime": "20101220233453.000", "PrimaryTag": "CC1", "Text": "STORM OVER THERE IN DECADES BUT "}
{"StartTime": "20101220233453.000", "EndTime": "20101220233454.000", "PrimaryTag": "CC1", "Text": "THE WEATHER DIDN'T STOP PRINCE  "}
{"StartTime": "20101220233454.000", "EndTime": "20101220233456.000", "PrimaryTag": "CC1", "Text": "WILLIAM AND KATE MIDDLETON FROM "}
{"StartTime": "20101220233456.000", "EndTime": "20101220233459.000", "PrimaryTag": "CC1", "Text": "MAKING THEIR FIRST PUBLIC       "}
{"StartTime": "20101220233459.000", "EndTime": "20101220233501.000", "PrimaryTag": "CC1", "Text": "APPEARANCE SINCE ANNOUNCING     "}
{"StartTime": "20101220233501.000", "EndTime": "20101220233502.000", "PrimaryTag": "CC1", "Text": "THEIR ENGAGEMENT.               "}
{"StartTime": "20101220233502.000", "EndTime": "20101220233508.000", "PrimaryTag": "CC1", "Text": "PRINCESS PACKAGE CONTINUES FOR  "}
{"StartTime": "20101220233508.000", "EndTime": "20101220233509.000", "PrimaryTag": "CC1", "Text": "KATE MIDDLETON.                 "}
{"StartTime": "20101220233509.000", "EndTime": "20101220233509.000", "PrimaryTag": "CC1", "Text": "THEY STEPPED OUT.               "}
{"StartTime": "20101220233509.000", "EndTime": "20101220233511.000", "PrimaryTag": "CC1", "Text": "THE HAPPY COUPLE WAS GREETED    "}
{"StartTime": "20101220233511.000", "EndTime": "20101220233512.000", "PrimaryTag": "CC1", "Text": "WITH APPLAUSE ARISING AT A      "}
{"StartTime": "20101220233512.000", "EndTime": "20101220233514.000", "PrimaryTag": "CC1", "Text": "CANCER CHARITY EVENT AND KATE   "}
{"StartTime": "20101220233514.000", "EndTime": "20101220233516.000", "PrimaryTag": "CC1", "Text": "LOOKED PRINCESS PERFECT IN A    "}
{"StartTime": "20101220233516.000", "EndTime": "20101220233518.000", "PrimaryTag": "CC1", "Text": "FLOWY WHITE DRESS WITH BLACK    "}
{"StartTime": "20101220233518.000", "EndTime": "20101220233523.000", "PrimaryTag": "CC1", "Text": "TRIM TOPPED WITH THE STRUCTURED "}
{"StartTime": "20101220233523.000", "EndTime": "20101220233524.000", "PrimaryTag": "CC1", "Text": "VELVET BLAZER.                  "}
{"StartTime": "20101220233524.000", "EndTime": "20101220233527.000", "PrimaryTag": "CC1", "Text": "LOOKS LIKE SHE HAS ONE DEVOTED  "}
{"StartTime": "20101220233527.000", "EndTime": "20101220233530.000", "PrimaryTag": "CC1", "Text": "FAN HER SOON TO BE BROTHER-IN-  "}
{"StartTime": "20101220233530.000", "EndTime": "20101220233535.000", "PrimaryTag": "CC1", "Text": "LAW PRINCE \"HARRY POTTER        "}
{"StartTime": "20101220233535.000", "EndTime": "20101220233535.000", "PrimaryTag": "CC1", "Text": "PRINCE HARRIRY.                 "}
{"StartTime": "20101220233535.000", "EndTime": "20101220233538.000", "PrimaryTag": "CC1", "Text": "HE SAID HE ALWAYS WANTED A      "}
{"StartTime": "20101220233538.000", "EndTime": "20101220233543.000", "PrimaryTag": "CC1", "Text": "SISTER AND NOW HE HAS ONE.      "}
{"StartTime": "20101220233543.000", "EndTime": "20101220233544.000", "PrimaryTag": "CC1", "Text": "THE ROYAL FAMILY JUST UNVEILED  "}
{"StartTime": "20101220233544.000", "EndTime": "20101220233550.000", "PrimaryTag": "CC1", "Text": "THE BONE CHINE WITH GOLD AND    "}
{"StartTime": "20101220233550.000", "EndTime": "20101220233552.000", "PrimaryTag": "CC1", "Text": "SILVER TRIM FEATURING WILLIAM   "}
{"StartTime": "20101220233552.000", "EndTime": "20101220233554.000", "PrimaryTag": "CC1", "Text": "AND KATHERINE'S INITIALS        "}
{"StartTime": "20101220233554.000", "EndTime": "20101220233554.000", "PrimaryTag": "CC1", "Text": "ENTWINED.                       "}
{"StartTime": "20101220233554.000", "EndTime": "20101220233555.000", "PrimaryTag": "CC1", "Text": "THIS MEMORABILIA DOESN'T COME   "}
{"StartTime": "20101220233555.000", "EndTime": "20101220233556.000", "PrimaryTag": "CC1", "Text": "CHEAP.                          "}
{"StartTime": "20101220233556.000", "EndTime": "20101220233600.000", "PrimaryTag": "CC1", "Text": "ONE PLATE COSTS $62 AND A ROYAL "}
{"StartTime": "20101220233600.000", "EndTime": "20101220233602.000", "PrimaryTag": "CC1", "Text": "PILL BOX GOES FOR $38.          "}
{"StartTime": "20101220233602.000", "EndTime": "20101220233610.000", "PrimaryTag": "CC1", "Text": ">>  Randy: PRINCESS DIANA'S     "}
{"StartTime": "20101220233610.000", "EndTime": "20101220233613.000", "PrimaryTag": "CC1", "Text": "FAME BIOGRAPHER ANDREW NORTON   "}
{"StartTime": "20101220233613.000", "EndTime": "20101220233615.000", "PrimaryTag": "CC1", "Text": "SAYS HE IS WORKING ON A BOOK    "}
{"StartTime": "20101220233615.000", "EndTime": "20101220233620.000", "PrimaryTag": "CC1", "Text": "FOR PRINCE WILLIAM AND KATE.    "}
{"StartTime": "20101220233620.000", "EndTime": "20101220233624.000", "PrimaryTag": "CC1", "Text": "PERSONNBERNARD MADOFF BECAME    "}
{"StartTime": "20101220233624.000", "EndTime": "20101220233626.000", "PrimaryTag": "CC1", "Text": "VERY DISTRAUGHT WHEN TOLD ABOUT "}
{"StartTime": "20101220233626.000", "EndTime": "20101220233627.000", "PrimaryTag": "CC1", "Text": "THE DEATH OF HIS SON.           "}
{"StartTime": "20101220233627.000", "EndTime": "20101220233632.000", "PrimaryTag": "CC1", "Text": "HE NEVER SHOWS EMOTION BUT NOW  "}
{"StartTime": "20101220233632.000", "EndTime": "20101220233633.000", "PrimaryTag": "CC1", "Text": "WE ARE LEARNING THAT BERNARD    "}
{"StartTime": "20101220233633.000", "EndTime": "20101220233636.000", "PrimaryTag": "CC1", "Text": "MADOFF BROKE DOWN SOBBING WHEN  "}
{"StartTime": "20101220233636.000", "EndTime": "20101220233640.000", "PrimaryTag": "CC1", "Text": "HE LEARNED OF HIS SON'S         "}
{"StartTime": "20101220233640.000", "EndTime": "20101220233641.000", "PrimaryTag": "CC1", "Text": "SUICIDE.                        "}
{"StartTime": "20101220233641.000", "EndTime": "20101220233642.000", "PrimaryTag": "CC1", "Text": "HE WAS CRYING AND VERY          "}
{"StartTime": "20101220233642.000", "EndTime": "20101220233642.000", "PrimaryTag": "CC1", "Text": "DISTRAUGHT.                     "}
{"StartTime": "20101220233642.000", "EndTime": "20101220233643.000", "PrimaryTag": "CC1", "Text": "ADDING THAT WHEN MADOFF WAS     "}
{"StartTime": "20101220233643.000", "EndTime": "20101220233645.000", "PrimaryTag": "CC1", "Text": "TOLD HIS SON MARK HAD TAKEN HIS "}
{"StartTime": "20101220233645.000", "EndTime": "20101220233648.000", "PrimaryTag": "CC1", "Text": "OWN LIFE HE LOOKED LIKE SOMEONE "}
{"StartTime": "20101220233648.000", "EndTime": "20101220233650.000", "PrimaryTag": "CC1", "Text": "HAD SHOT HIM IN THE STOMACH.    "}
{"StartTime": "20101220233650.000", "EndTime": "20101220233651.000", "PrimaryTag": "CC1", "Text": "BERNARD MADOFF BIOGRAPHER.      "}
{"StartTime": "20101220233651.000", "EndTime": "20101220233655.000", "PrimaryTag": "CC1", "Text": ">>  Randy: MADOFF SHOWED NO     "}
{"StartTime": "20101220233655.000", "EndTime": "20101220233656.000", "PrimaryTag": "CC1", "Text": "REMORSE ABOUT BANKRUPTING HIS   "}
{"StartTime": "20101220233656.000", "EndTime": "20101220233701.000", "PrimaryTag": "CC1", "Text": "BEST FRIEND BUT HE TOOK PRETTY  "}
{"StartTime": "20101220233701.000", "EndTime": "20101220233704.000", "PrimaryTag": "CC1", "Text": "GOOD CARE OF HIS WIFE AND       "}
{"StartTime": "20101220233704.000", "EndTime": "20101220233705.000", "PrimaryTag": "CC1", "Text": "FAMILY.                         "}
{"StartTime": "20101220233705.000", "EndTime": "20101220233707.000", "PrimaryTag": "CC1", "Text": "I DON'T DOUBT HE IS DEVASTATED  "}
{"StartTime": "20101220233707.000", "EndTime": "20101220233707.000", "PrimaryTag": "CC1", "Text": "BY THIS.                        "}
{"StartTime": "20101220233707.000", "EndTime": "20101220233710.000", "PrimaryTag": "CC1", "Text": ">> THE WORLD WAS SHOCKED BY THE "}
{"StartTime": "20101220233710.000", "EndTime": "20101220233712.000", "PrimaryTag": "CC1", "Text": "DEATH OF MARK MADOFF WHO HUNG   "}
{"StartTime": "20101220233712.000", "EndTime": "20101220233714.000", "PrimaryTag": "CC1", "Text": "HIMSELF FROM HIS LOFT IN        "}
{"StartTime": "20101220233714.000", "EndTime": "20101220233715.000", "PrimaryTag": "CC1", "Text": "MANHATTAN.                      "}
{"StartTime": "20101220233715.000", "EndTime": "20101220233715.000", "PrimaryTag": "CC1", "Text": "BERNARD MADOFF WAS NOTIFIED     "}
{"StartTime": "20101220233715.000", "EndTime": "20101220233717.000", "PrimaryTag": "CC1", "Text": "ABOUT THE TRAGEDY ABOUT FIVE    "}
{"StartTime": "20101220233717.000", "EndTime": "20101220233719.000", "PrimaryTag": "CC1", "Text": "HOURS AFTER IT HAPPENED.        "}
{"StartTime": "20101220233719.000", "EndTime": "20101220233723.000", "PrimaryTag": "CC1", "Text": "ACCORDING TO THE EX-CONA        "}
{"StartTime": "20101220233723.000", "EndTime": "20101220233724.000", "PrimaryTag": "CC1", "Text": "SOBBING BERNARD MADOFF RETURNED "}
{"StartTime": "20101220233724.000", "EndTime": "20101220233726.000", "PrimaryTag": "CC1", "Text": "TO HIS CELL TO TWO DAYS         "}
{"StartTime": "20101220233726.000", "EndTime": "20101220233727.000", "PrimaryTag": "CC1", "Text": "DEVASTATED THAT NO FAMILY       "}
{"StartTime": "20101220233727.000", "EndTime": "20101220233728.000", "PrimaryTag": "CC1", "Text": "MEMBERS CAME TO VISIT HIM.      "}
{"StartTime": "20101220233728.000", "EndTime": "20101220233730.000", "PrimaryTag": "CC1", "Text": "IT IS ONLY NOW THAT HE          "}
{"StartTime": "20101220233730.000", "EndTime": "20101220233732.000", "PrimaryTag": "CC1", "Text": "CAUSEDDED DEATH OF ONE OF HIS   "}
{"StartTime": "20101220233732.000", "EndTime": "20101220233737.000", "PrimaryTag": "CC1", "Text": "BELOVED  SONS.                  "}
{"StartTime": "20101220233737.000", "EndTime": "20101220233740.000", "PrimaryTag": "CC1", "Text": "I THINK HE WILL REALLY SUFFER.  "}
{"StartTime": "20101220233740.000", "EndTime": "20101220233741.000", "PrimaryTag": "CC1", "Text": "HE IS SAID TO BE UPSET THAT HIS "}
{"StartTime": "20101220233741.000", "EndTime": "20101220233747.000", "PrimaryTag": "CC1", "Text": "WIFE DIDN'T COME TO GRIEVE WITH "}
{"StartTime": "20101220233747.000", "EndTime": "20101220233747.000", "PrimaryTag": "CC1", "Text": "HIM.                            "}
{"StartTime": "20101220233747.000", "EndTime": "20101220233748.000", "PrimaryTag": "CC1", "Text": ">> A FAMOUS SOAP STAR BACKING   "}
{"StartTime": "20101220233748.000", "EndTime": "20101220233750.000", "PrimaryTag": "CC1", "Text": "OUT OF AN APPEARANCE.           "}
{"StartTime": "20101220233750.000", "EndTime": "20101220233752.000", "PrimaryTag": "CC1", "Text": ">>  Randy: NEIL PATRICK HARRIS  "}
{"StartTime": "20101220233752.000", "EndTime": "20101220233754.000", "PrimaryTag": "CC1", "Text": "CALLING ANOTHER ACTOR A D-BAG.  "}
{"StartTime": "20101220233754.000", "EndTime": "20101220233757.000", "PrimaryTag": "CC1", "Text": "THE HOW I MET YOUR MOTHER STAR  "}
{"StartTime": "20101220233757.000", "EndTime": "20101220233759.000", "PrimaryTag": "CC1", "Text": "WAS FITTING MAD BECAUSE VETERAN "}
{"StartTime": "20101220233759.000", "EndTime": "20101220233806.000", "PrimaryTag": "CC1", "Text": "SOAP STAR ERIC BRADDEN CANCELED "}
{"StartTime": "20101220233806.000", "EndTime": "20101220233809.000", "PrimaryTag": "CC1", "Text": "A GUEST APPEARANCE.             "}
{"StartTime": "20101220233809.000", "EndTime": "20101220233810.000", "PrimaryTag": "CC1", "Text": "HARRIS TWEETED BRADDEN IS D-    "}
{"StartTime": "20101220233810.000", "EndTime": "20101220233810.000", "PrimaryTag": "CC1", "Text": "BAG.                            "}
{"StartTime": "20101220233810.000", "EndTime": "20101220233811.000", "PrimaryTag": "CC1", "Text": "BRADDEN WHO APPEARED ON THE     "}
{"StartTime": "20101220233811.000", "EndTime": "20101220233813.000", "PrimaryTag": "CC1", "Text": "YOUNG AND RESTLY FOR 30 YEARS   "}
{"StartTime": "20101220233813.000", "EndTime": "20101220233814.000", "PrimaryTag": "CC1", "Text": "WASN'T PULLING A STAR TRIP.     "}
{"StartTime": "20101220233814.000", "EndTime": "20101220233816.000", "PrimaryTag": "CC1", "Text": "THE 69 YEAR OLD WAS RECOVERING  "}
{"StartTime": "20101220233816.000", "EndTime": "20101220233816.000", "PrimaryTag": "CC1", "Text": "FROM HIP REPLACEMENT SURGERY    "}
{"StartTime": "20101220233816.000", "EndTime": "20101220233818.000", "PrimaryTag": "CC1", "Text": "AND DIDN'T WANT TO TRAVEL FROM  "}
{"StartTime": "20101220233818.000", "EndTime": "20101220233820.000", "PrimaryTag": "CC1", "Text": "NEW YORK TO L.A.                "}
{"StartTime": "20101220233820.000", "EndTime": "20101220233821.000", "PrimaryTag": "CC1", "Text": "FOR A FEW LINES.                "}
{"StartTime": "20101220233821.000", "EndTime": "20101220233823.000", "PrimaryTag": "CC1", "Text": "HE STRUCK BACK SAYING HARRIS IS "}
{"StartTime": "20101220233823.000", "EndTime": "20101220233824.000", "PrimaryTag": "CC1", "Text": "LIKE A YOUNG WHIPPER SNAPPER    "}
{"StartTime": "20101220233824.000", "EndTime": "20101220233826.000", "PrimaryTag": "CC1", "Text": "WHO HAS RECEIVED A FEW AWARDS   "}
{"StartTime": "20101220233826.000", "EndTime": "20101220233829.000", "PrimaryTag": "CC1", "Text": "AND IS NOW SUDDENLY SUFFERING   "}
{"StartTime": "20101220233829.000", "EndTime": "20101220233830.000", "PrimaryTag": "CC1", "Text": "FROM THE FIRST SIGN.            "}
{"StartTime": "20101220233830.000", "EndTime": "20101220233831.000", "PrimaryTag": "CC1", "Text": "AND HARRIS BACKED OFF TWEETING  "}
{"StartTime": "20101220233831.000", "EndTime": "20101220233835.000", "PrimaryTag": "CC1", "Text": "NOW I FEEL BAD FOR THE D-BAG    "}
{"StartTime": "20101220233835.000", "EndTime": "20101220233835.000", "PrimaryTag": "CC1", "Text": "COMMENT.                        "}
{"StartTime": "20101220233835.000", "EndTime": "20101220233837.000", "PrimaryTag": "CC1", "Text": "DON'T KNOW THE GUY PERSONALLY.  "}
{"StartTime": "20101220233837.000", "EndTime": "20101220233844.000", "PrimaryTag": "CC1", "Text": "I'M JUST FIERCELY PROTECTIVE OF "}
{"StartTime": "20101220233844.000", "EndTime": "20101220233849.000", "PrimaryTag": "CC1", "Text": "OUR  SHOW.                      "}
{"StartTime": "20101220233849.000", "EndTime": "20101220233850.000", "PrimaryTag": "CC1", "Text": ">> KATE HOLMES CELEBRATED HER   "}
{"StartTime": "20101220233850.000", "EndTime": "20101220233900.000", "PrimaryTag": "CC1", "Text": "31st  3 -- -- 32nd BIRTHDAY.    "}
{"StartTime": "20101220233900.000", "EndTime": "20101220233903.000", "PrimaryTag": "CC1", "Text": "TOM CRUZ TOOK HER TO TWO        "}
{"StartTime": "20101220233903.000", "EndTime": "20101220233909.000", "PrimaryTag": "CC1", "Text": "RESTAURANTS, ONE FOR DINNER AND "}
{"StartTime": "20101220233909.000", "EndTime": "20101220233910.000", "PrimaryTag": "CC1", "Text": "ONE FOR DESSERT.                "}
{"StartTime": "20101220233910.000", "EndTime": "20101220233913.000", "PrimaryTag": "CC1", "Text": "THAT'S CAMERON DIAZ WITH ALEX   "}
{"StartTime": "20101220233913.000", "EndTime": "20101220233914.000", "PrimaryTag": "CC1", "Text": "RODRIGUEZ'S DAUGHTERS IN        "}
{"StartTime": "20101220233914.000", "EndTime": "20101220233914.000", "PrimaryTag": "CC1", "Text": "MEXICO.                         "}
{"StartTime": "20101220233914.000", "EndTime": "20101220233919.000", "PrimaryTag": "CC1", "Text": "TAKE A LOOK AT THIS.            "}
{"StartTime": "20101220233919.000", "EndTime": "20101220233921.000", "PrimaryTag": "CC1", "Text": "GYM JAB IS BACK ON THEIR TAKE   "}
{"StartTime": "20101220233921.000", "EndTime": "20101220233925.000", "PrimaryTag": "CC1", "Text": "ON HOW PRESIDENT OBAMA AND JOE  "}
{"StartTime": "20101220233925.000", "EndTime": "20101220233925.000", "PrimaryTag": "CC1", "Text": "BIDEN FEEL ABOUT 2010.          "}
{"StartTime": "20101220233925.000", "EndTime": "20101220233926.000", "PrimaryTag": "CC1", "Text": "? 2010.                         "}
{"StartTime": "20101220233926.000", "EndTime": "20101220233937.000", "PrimaryTag": "CC1", "Text": "CAN'T WAIT FOR YOU JUST LIKE    "}
{"StartTime": "20101220233937.000", "EndTime": "20101220233942.000", "PrimaryTag": "CC1", "Text": "THAT GUY FROM JET BLUE.         "}
{"StartTime": "20101220233942.000", "EndTime": "20101220233949.000", "PrimaryTag": "CC1", "Text": "?[ MUSIC ]?                     "}
{"StartTime": "20101220233949.000", "EndTime": "20101220233950.000", "PrimaryTag": "CC1", "Text": "SPEAKING OF WRAPPING UP 2010 A  "}
{"StartTime": "20101220233950.000", "EndTime": "20101220233952.000", "PrimaryTag": "CC1", "Text": "BIT LATER IN THE BROADCAST WE   "}
{"StartTime": "20101220233952.000", "EndTime": "20101220234000.000", "PrimaryTag": "CC1", "Text": "WILL HAVE A LOOK BACK WHO TREAT "}
{"StartTime": "20101220234000.000", "EndTime": "20101220234001.000", "PrimaryTag": "CC1", "Text": "WAS ON THE RED CARPET.          "}
{"StartTime": "20101220234001.000", "EndTime": "20101220234007.000", "PrimaryTag": "CC1", "Text": ">> COULD THESE AS WELL BE       "}
{"StartTime": "20101220234007.000", "EndTime": "20101220234009.000", "PrimaryTag": "CC1", "Text": "VICTIMS OF THE SUSPECTED SERIAL "}
{"StartTime": "20101220234009.000", "EndTime": "20101220234012.000", "PrimaryTag": "CC1", "Text": "KILLER COPS CALL THE GRIM       "}
{"StartTime": "20101220234012.000", "EndTime": "20101220234012.000", "PrimaryTag": "CC1", "Text": "SLEEPER.                        "}
{"StartTime": "20101220234012.000", "EndTime": "20101220234013.000", "PrimaryTag": "CC1", "Text": "PHOTOS OF 180 WOMEN.            "}
{"StartTime": "20101220234013.000", "EndTime": "20101220234015.000", "PrimaryTag": "CC1", "Text": "WHY DO SO MANY SEEM TO BE       "}
{"StartTime": "20101220234015.000", "EndTime": "20101220234015.000", "PrimaryTag": "CC1", "Text": "SLEEPING?                       "}
{"StartTime": "20101220234015.000", "EndTime": "20101220234018.000", "PrimaryTag": "CC1", "Text": "THE BRIDE'S SEARCH FOR THE GUYS "}
{"StartTime": "20101220234018.000", "EndTime": "20101220234020.000", "PrimaryTag": "CC1", "Text": "WHO TOOK HER WEDDING DRESS.     "}
{"StartTime": "20101220234020.000", "EndTime": "20101220234023.000", "PrimaryTag": "CC1", "Text": ">> I'M GOING TO CATCH THE PUNKS "}
{"StartTime": "20101220234023.000", "EndTime": "20101220234024.000", "PrimaryTag": "CC1", "Text": "THAT DID THIS.                  "}
{"StartTime": "20101220234024.000", "EndTime": "20101220234026.000", "PrimaryTag": "CC1", "Text": ">> REAL LIFE NANCY DREW.        "}
{"StartTime": "20101220234026.000", "EndTime": "20101220234035.000", "PrimaryTag": "CC1", "Text": "HOW SHE TRACKS DOWN THE CROOK.  "}
{"StartTime": "20101220234035.000", "EndTime": "20101220234036.000", "PrimaryTag": "CC1", "Text": ">> THAT'S MY DRESS.             "}
{"StartTime": "20101220234036.000", "EndTime": "20101220234040.000", "PrimaryTag": "CC1", "Text": ">> A BOY WRAPPED UP LIKE A      "}
{"StartTime": "20101220234040.000", "EndTime": "20101220234041.000", "PrimaryTag": "CC1", "Text": "MUMMY.                          "}
{"StartTime": "20101220234041.000", "EndTime": "20101220234234.000", "PrimaryTag": "CC1", "Text": "PLUS THE RED CARPET MOMENTS OF  "}
{"StartTime": "20101220234234.000", "EndTime": "20101220234340.000", "PrimaryTag": "SEG_01", "Type": "Commercial"}
{"StartTime": "20101220234234.000", "EndTime": "20101220234236.000", "PrimaryTag": "CC1", "Text": "        Are you trapped         "}
{"StartTime": "20101220234236.000", "EndTime": "20101220234236.000", "PrimaryTag": "CC1", "Text": "  and don't know how to escape  "}
{"StartTime": "20101220234236.000", "EndTime": "20101220234240.000", "PrimaryTag": "CC1", "Text": " your addiction to cigarettes?  "}
{"StartTime": "20101220234240.000", "EndTime": "20101220234240.000", "PrimaryTag": "CC1", "Text": " One out of two regular smokers "}
{"StartTime": "20101220234240.000", "EndTime": "20101220234240.000", "PrimaryTag": "CC1", "Text": "   will die prematurely from    "}
{"StartTime": "20101220234240.000", "EndTime": "20101220234246.000", "PrimaryTag": "CC1", "Text": "           smoking.             "}
{"StartTime": "20101220234246.000", "EndTime": "20101220234246.000", "PrimaryTag": "CC1", "Text": "  You don't have to be one of   "}
{"StartTime": "20101220234246.000", "EndTime": "20101220234249.000", "PrimaryTag": "CC1", "Text": "             them.              "}
{"StartTime": "20101220234249.000", "EndTime": "20101220234251.000", "PrimaryTag": "CC1", "Text": "        Escape the trap.        "}
{"StartTime": "20101220234251.000", "EndTime": "20101220234254.000", "PrimaryTag": "CC1", "Text": "         Say \"Enough.\"          "}
{"StartTime": "20101220234254.000", "EndTime": "20101220234254.000", "PrimaryTag": "CC1", "Text": " For free help to quit smoking, "}
{"StartTime": "20101220234254.000", "EndTime": "20101220234254.000", "PrimaryTag": "CC1", "Text": "  call the California Smokers'  "}
{"StartTime": "20101220234254.000", "EndTime": "20101220234257.000", "PrimaryTag": "CC1", "Text": "          Helpline at           "}
{"StartTime": "20101220234257.000", "EndTime": "20101220234340.000", "PrimaryTag": "CC1", "Text": "        1-800-NO BUTTS.         "}
{"StartTime": "20101220234340.000", "EndTime": "20101220234343.000", "PrimaryTag": "SEG_01", "Type": "Story start"}
{"StartTime": "20101220234340.000", "EndTime": "20101220234343.000", "PrimaryTag": "CC1", "Text": ">> WILLIAM AND KATE THE UNTOLD  "}
{"StartTime": "20101220234343.000", "EndTime": "20101220234344.000", "PrimaryTag": "CC1", "Text": "STORY.                          "}
{"StartTime": "20101220234344.000", "EndTime": "20101220234345.000", "PrimaryTag": "CC1", "Text": "THE NEW BOOK ABOUT THEIR        "}
{"StartTime": "20101220234345.000", "EndTime": "20101220234346.000", "PrimaryTag": "CC1", "Text": "ROMANCE.                        "}
{"StartTime": "20101220234346.000", "EndTime": "20101220234346.000", "PrimaryTag": "CC1", "Text": "HOW PRINCE WILLIAM BROKE UP     "}
{"StartTime": "20101220234346.000", "EndTime": "20101220234350.000", "PrimaryTag": "CC1", "Text": "WITH KATE BY CELL PHONE AND HOW "}
{"StartTime": "20101220234350.000", "EndTime": "20101220234350.000", "PrimaryTag": "CC1", "Text": "HE WON HER BACK.                "}
{"StartTime": "20101220234350.000", "EndTime": "20101220234354.000", "PrimaryTag": "CC1", "Text": ">>  Deborah: WHO ARE THESE      "}
{"StartTime": "20101220234354.000", "EndTime": "20101220234354.000", "PrimaryTag": "CC1", "Text": "WOMEN?                          "}
{"StartTime": "20101220234354.000", "EndTime": "20101220234355.000", "PrimaryTag": "CC1", "Text": "THESE PHOTOS ARE AMONG MORE     "}
{"StartTime": "20101220234355.000", "EndTime": "20101220234356.000", "PrimaryTag": "CC1", "Text": "THAN 180 THAT WERE FOUND IN THE "}
{"StartTime": "20101220234356.000", "EndTime": "20101220234359.000", "PrimaryTag": "CC1", "Text": "HOME OF A MAN THAT L.A.         "}
{"StartTime": "20101220234359.000", "EndTime": "20101220234401.000", "PrimaryTag": "CC1", "Text": "POLICE SAY IS A NOTORIOUS       "}
{"StartTime": "20101220234401.000", "EndTime": "20101220234403.000", "PrimaryTag": "CC1", "Text": "SERIAL KILLER CALLED THE GRIM   "}
{"StartTime": "20101220234403.000", "EndTime": "20101220234403.000", "PrimaryTag": "CC1", "Text": "SLEEPER.                        "}
{"StartTime": "20101220234403.000", "EndTime": "20101220234405.000", "PrimaryTag": "CC1", "Text": "SO FAR HE HAS BEEN CHARGED WITH "}
{"StartTime": "20101220234405.000", "EndTime": "20101220234407.000", "PrimaryTag": "CC1", "Text": "TEN KILLINGS BUT AS JIM MORET   "}
{"StartTime": "20101220234407.000", "EndTime": "20101220234408.000", "PrimaryTag": "CC1", "Text": "REPORTS BASED ON THIS           "}
{"StartTime": "20101220234408.000", "EndTime": "20101220234409.000", "PrimaryTag": "CC1", "Text": "COLLECTION OF PHOTOS            "}
{"StartTime": "20101220234409.000", "EndTime": "20101220234410.000", "PrimaryTag": "CC1", "Text": "AUTHORITIES FEAR THERE MAY BE   "}
{"StartTime": "20101220234410.000", "EndTime": "20101220234410.000", "PrimaryTag": "CC1", "Text": "MANY MORE.                      "}
{"StartTime": "20101220234410.000", "EndTime": "20101220234412.000", "PrimaryTag": "CC1", "Text": ">> THEY ARE THE MYSTERY WOMEN   "}
{"StartTime": "20101220234412.000", "EndTime": "20101220234415.000", "PrimaryTag": "CC1", "Text": "AT THE CENTER OF AN HORRIFIC    "}
{"StartTime": "20101220234415.000", "EndTime": "20101220234416.000", "PrimaryTag": "CC1", "Text": "SERIAL KILLER CASE.             "}
{"StartTime": "20101220234416.000", "EndTime": "20101220234418.000", "PrimaryTag": "CC1", "Text": "THESE PHOTOS, 180 OF THEM, WERE "}
{"StartTime": "20101220234418.000", "EndTime": "20101220234420.000", "PrimaryTag": "CC1", "Text": "FOUND OMINOUSLY IN THE          "}
{"StartTime": "20101220234420.000", "EndTime": "20101220234421.000", "PrimaryTag": "CC1", "Text": "POSSESSION OF A SUSPECTED MASS  "}
{"StartTime": "20101220234421.000", "EndTime": "20101220234422.000", "PrimaryTag": "CC1", "Text": "MURDER.                         "}
{"StartTime": "20101220234422.000", "EndTime": "20101220234424.000", "PrimaryTag": "CC1", "Text": "NOW COPS ARE APPEALING FOR HELP "}
{"StartTime": "20101220234424.000", "EndTime": "20101220234426.000", "PrimaryTag": "CC1", "Text": "IN PUTTING NAMES TO THESE FACES "}
{"StartTime": "20101220234426.000", "EndTime": "20101220234428.000", "PrimaryTag": "CC1", "Text": "TO ESTABLISH IF THE             "}
{"StartTime": "20101220234428.000", "EndTime": "20101220234430.000", "PrimaryTag": "CC1", "Text": "UNIDENTIFIED WOMEN ARE ALIVE OR "}
{"StartTime": "20101220234430.000", "EndTime": "20101220234430.000", "PrimaryTag": "CC1", "Text": "DEAD.                           "}
{"StartTime": "20101220234430.000", "EndTime": "20101220234431.000", "PrimaryTag": "CC1", "Text": ">> THERE IS SOMEBODY'S PHOTO    "}
{"StartTime": "20101220234431.000", "EndTime": "20101220234433.000", "PrimaryTag": "CC1", "Text": "AMONG THESE 180 WHO IS A        "}
{"StartTime": "20101220234433.000", "EndTime": "20101220234433.000", "PrimaryTag": "CC1", "Text": "VICTIM.                         "}
{"StartTime": "20101220234433.000", "EndTime": "20101220234434.000", "PrimaryTag": "CC1", "Text": ">> THE PHOTOS WERE FOUND WHEN   "}
{"StartTime": "20101220234434.000", "EndTime": "20101220234437.000", "PrimaryTag": "CC1", "Text": "COPS SEARCHED THE HOME OF A     "}
{"StartTime": "20101220234437.000", "EndTime": "20101220234439.000", "PrimaryTag": "CC1", "Text": "FORMER POLICE DEPARTMENT        "}
{"StartTime": "20101220234439.000", "EndTime": "20101220234441.000", "PrimaryTag": "CC1", "Text": "EMPLOYEE NAMED LONNIE FRANKLIN. "}
{"StartTime": "20101220234441.000", "EndTime": "20101220234442.000", "PrimaryTag": "CC1", "Text": "AUTHORITIES BELIEVE FRANKLIN IS "}
{"StartTime": "20101220234442.000", "EndTime": "20101220234444.000", "PrimaryTag": "CC1", "Text": "THE MYSTERIOUS SERIAL KILLER    "}
{"StartTime": "20101220234444.000", "EndTime": "20101220234445.000", "PrimaryTag": "CC1", "Text": "DUBBING THE GRIM SLEEPER WHO    "}
{"StartTime": "20101220234445.000", "EndTime": "20101220234446.000", "PrimaryTag": "CC1", "Text": "TERRORIZED LOS ANGELES FOR MORE "}
{"StartTime": "20101220234446.000", "EndTime": "20101220234447.000", "PrimaryTag": "CC1", "Text": "THAN TWO DECADES.               "}
{"StartTime": "20101220234447.000", "EndTime": "20101220234448.000", "PrimaryTag": "CC1", "Text": "WHY THE NICKNAME THE GRIM       "}
{"StartTime": "20101220234448.000", "EndTime": "20101220234449.000", "PrimaryTag": "CC1", "Text": "SLEEPER?                        "}
{"StartTime": "20101220234449.000", "EndTime": "20101220234451.000", "PrimaryTag": "CC1", "Text": "WELL, THE CASE STARTED BACK IN  "}
{"StartTime": "20101220234451.000", "EndTime": "20101220234452.000", "PrimaryTag": "CC1", "Text": "THE LATE 1980s WHEN SOMEONE     "}
{"StartTime": "20101220234452.000", "EndTime": "20101220234453.000", "PrimaryTag": "CC1", "Text": "CARRIED OUT A STRING OF MURDERS "}
{"StartTime": "20101220234453.000", "EndTime": "20101220234456.000", "PrimaryTag": "CC1", "Text": "OF YOUNG WOMEN ON THE STREETS   "}
{"StartTime": "20101220234456.000", "EndTime": "20101220234502.000", "PrimaryTag": "CC1", "Text": "OF SOUTH LOS ANGELES.           "}
{"StartTime": "20101220234502.000", "EndTime": "20101220234506.000", "PrimaryTag": "CC1", "Text": "THEN THE KILLINGS APPARENTLY    "}
{"StartTime": "20101220234506.000", "EndTime": "20101220234508.000", "PrimaryTag": "CC1", "Text": "STOPPED AND THEN STARTED IN     "}
{"StartTime": "20101220234508.000", "EndTime": "20101220234508.000", "PrimaryTag": "CC1", "Text": "2002.                           "}
{"StartTime": "20101220234508.000", "EndTime": "20101220234509.000", "PrimaryTag": "CC1", "Text": "FRANKLIN WAS ARRESTED THIS      "}
{"StartTime": "20101220234509.000", "EndTime": "20101220234510.000", "PrimaryTag": "CC1", "Text": "SUMMER AFTER COPS SAY DNA       "}
{"StartTime": "20101220234510.000", "EndTime": "20101220234512.000", "PrimaryTag": "CC1", "Text": "LINKED HIM TO SEVERAL OF THE    "}
{"StartTime": "20101220234512.000", "EndTime": "20101220234513.000", "PrimaryTag": "CC1", "Text": "GRIM  SLEEPER KILLINGS.         "}
{"StartTime": "20101220234513.000", "EndTime": "20101220234516.000", "PrimaryTag": "CC1", "Text": "THE MAYOR OF LOS ANGELES        "}
{"StartTime": "20101220234516.000", "EndTime": "20101220234516.000", "PrimaryTag": "CC1", "Text": "DESCRIBED FRANKLIN'S ARREST     "}
{"StartTime": "20101220234516.000", "EndTime": "20101220234517.000", "PrimaryTag": "CC1", "Text": "THIS WAY.                       "}
{"StartTime": "20101220234517.000", "EndTime": "20101220234518.000", "PrimaryTag": "CC1", "Text": ">> TERROR IN OUR CITY CAME TO   "}
{"StartTime": "20101220234518.000", "EndTime": "20101220234519.000", "PrimaryTag": "CC1", "Text": "AN END.                         "}
{"StartTime": "20101220234519.000", "EndTime": "20101220234521.000", "PrimaryTag": "CC1", "Text": ">> SINCE THE PHOTOS WERE        "}
{"StartTime": "20101220234521.000", "EndTime": "20101220234522.000", "PrimaryTag": "CC1", "Text": "RELEASED POLICE HAD BEEN        "}
{"StartTime": "20101220234522.000", "EndTime": "20101220234524.000", "PrimaryTag": "CC1", "Text": "SWAMPED WITH TIPS AND HAVE      "}
{"StartTime": "20101220234524.000", "EndTime": "20101220234524.000", "PrimaryTag": "CC1", "Text": "TENTATIVELY IDENTIFIED A        "}
{"StartTime": "20101220234524.000", "EndTime": "20101220234526.000", "PrimaryTag": "CC1", "Text": "HANDFUL OF WOMEN BUT THE VAST   "}
{"StartTime": "20101220234526.000", "EndTime": "20101220234527.000", "PrimaryTag": "CC1", "Text": "MAJORITY ARE STILL UNNAMED.     "}
{"StartTime": "20101220234527.000", "EndTime": "20101220234529.000", "PrimaryTag": "CC1", "Text": ">> WE HAVE NO IDEA WHO THEY     "}
{"StartTime": "20101220234529.000", "EndTime": "20101220234531.000", "PrimaryTag": "CC1", "Text": "ARE, WHAT THE RELATIONSHIP IS.  "}
{"StartTime": "20101220234531.000", "EndTime": "20101220234533.000", "PrimaryTag": "CC1", "Text": "THE BOTTOM LINE IS TO IDENTIFY  "}
{"StartTime": "20101220234533.000", "EndTime": "20101220234537.000", "PrimaryTag": "CC1", "Text": "THEM, SPEAK TO THEM, AND        "}
{"StartTime": "20101220234537.000", "EndTime": "20101220234538.000", "PrimaryTag": "CC1", "Text": "ACCOUNT FOR THEIR WELFARE.      "}
{"StartTime": "20101220234538.000", "EndTime": "20101220234540.000", "PrimaryTag": "CC1", "Text": ">> DIANA WARE IS THE STEPMOTHER "}
{"StartTime": "20101220234540.000", "EndTime": "20101220234543.000", "PrimaryTag": "CC1", "Text": "OF THE WOMAN WHO POLICE SAY IS  "}
{"StartTime": "20101220234543.000", "EndTime": "20101220234545.000", "PrimaryTag": "CC1", "Text": "THE GRIM SLEEPER AREAS FOURTH   "}
{"StartTime": "20101220234545.000", "EndTime": "20101220234546.000", "PrimaryTag": "CC1", "Text": "VICTIM.                         "}
{"StartTime": "20101220234546.000", "EndTime": "20101220234547.000", "PrimaryTag": "CC1", "Text": "WHEN SHE SEES THOSE SCORES OF   "}
{"StartTime": "20101220234547.000", "EndTime": "20101220234549.000", "PrimaryTag": "CC1", "Text": "UNIDENTIFIED WOMEN SHE FEARS    "}
{"StartTime": "20101220234549.000", "EndTime": "20101220234549.000", "PrimaryTag": "CC1", "Text": "THE WORSE.                      "}
{"StartTime": "20101220234549.000", "EndTime": "20101220234552.000", "PrimaryTag": "CC1", "Text": ">> THEY HAVEN'T FOUND OTHER     "}
{"StartTime": "20101220234552.000", "EndTime": "20101220234554.000", "PrimaryTag": "CC1", "Text": "VICTIMS YET AND I REALLY HATE   "}
{"StartTime": "20101220234554.000", "EndTime": "20101220234557.000", "PrimaryTag": "CC1", "Text": "TO THINK HOW MANY THERE COULD   "}
{"StartTime": "20101220234557.000", "EndTime": "20101220234557.000", "PrimaryTag": "CC1", "Text": "BE.                             "}
{"StartTime": "20101220234557.000", "EndTime": "20101220234559.000", "PrimaryTag": "CC1", "Text": ">> FRANKLIN, A FORMER POLICE    "}
{"StartTime": "20101220234559.000", "EndTime": "20101220234601.000", "PrimaryTag": "CC1", "Text": "GARAGE ATTENDANT HAS PLEADED    "}
{"StartTime": "20101220234601.000", "EndTime": "20101220234602.000", "PrimaryTag": "CC1", "Text": "NOT GUILTY TO 10 MURDER         "}
{"StartTime": "20101220234602.000", "EndTime": "20101220234603.000", "PrimaryTag": "CC1", "Text": "CHARGES.                        "}
{"StartTime": "20101220234603.000", "EndTime": "20101220234605.000", "PrimaryTag": "CC1", "Text": ">> PROSECUTORS SAY THEY PLAN TO "}
{"StartTime": "20101220234605.000", "EndTime": "20101220234607.000", "PrimaryTag": "CC1", "Text": "SEEK THE DEATH PENALTY.         "}
{"StartTime": "20101220234607.000", "EndTime": "20101220234608.000", "PrimaryTag": "CC1", "Text": ">> A WOMAN ON A MISSION.        "}
{"StartTime": "20101220234608.000", "EndTime": "20101220234610.000", "PrimaryTag": "CC1", "Text": "WHEN THIS BRIDE FOUND OUT THAT  "}
{"StartTime": "20101220234610.000", "EndTime": "20101220234612.000", "PrimaryTag": "CC1", "Text": "SOME PUNKS STOLE HER WEDDING    "}
{"StartTime": "20101220234612.000", "EndTime": "20101220234614.000", "PrimaryTag": "CC1", "Text": "DRESS SHE WENT INTO ACTION.     "}
{"StartTime": "20101220234614.000", "EndTime": "20101220234615.000", "PrimaryTag": "CC1", "Text": "SHE TRACKED THE THIEVES DOWN    "}
{"StartTime": "20101220234615.000", "EndTime": "20101220234618.000", "PrimaryTag": "CC1", "Text": "ONLINE AND THEN SET UP A STING  "}
{"StartTime": "20101220234618.000", "EndTime": "20101220234619.000", "PrimaryTag": "CC1", "Text": "TO GET HER GOWN BACK.           "}
{"StartTime": "20101220234619.000", "EndTime": "20101220234621.000", "PrimaryTag": "CC1", "Text": ">> A YOUNG WOMAN GETS           "}
{"StartTime": "20101220234621.000", "EndTime": "20101220234624.000", "PrimaryTag": "CC1", "Text": "DISTURBING NEWS THAT HER        "}
{"StartTime": "20101220234624.000", "EndTime": "20101220234626.000", "PrimaryTag": "CC1", "Text": "STORAGE LOCKER HAD BEEN BROKEN  "}
{"StartTime": "20101220234626.000", "EndTime": "20101220234627.000", "PrimaryTag": "CC1", "Text": "INTO.                           "}
{"StartTime": "20101220234627.000", "EndTime": "20101220234628.000", "PrimaryTag": "CC1", "Text": "ELAINA DISCOVERED IT WAS        "}
{"StartTime": "20101220234628.000", "EndTime": "20101220234629.000", "PrimaryTag": "CC1", "Text": "COMPLETELY RANSACKED.           "}
{"StartTime": "20101220234629.000", "EndTime": "20101220234630.000", "PrimaryTag": "CC1", "Text": "BUT THEN HER HEART SANK.        "}
{"StartTime": "20101220234630.000", "EndTime": "20101220234631.000", "PrimaryTag": "CC1", "Text": ">> FIRST THING I SAW WAS THE    "}
{"StartTime": "20101220234631.000", "EndTime": "20101220234633.000", "PrimaryTag": "CC1", "Text": "BOX THAT MY WEDDING DRESS CAME  "}
{"StartTime": "20101220234633.000", "EndTime": "20101220234634.000", "PrimaryTag": "CC1", "Text": "IN, IT WAS EMPTY.               "}
{"StartTime": "20101220234634.000", "EndTime": "20101220234636.000", "PrimaryTag": "CC1", "Text": ">> MARRIED JUST WOULD YEARS AGO "}
{"StartTime": "20101220234636.000", "EndTime": "20101220234638.000", "PrimaryTag": "CC1", "Text": "THE MEMORY OF WEARING HER       "}
{"StartTime": "20101220234638.000", "EndTime": "20101220234640.000", "PrimaryTag": "CC1", "Text": "PRECIOUS WEDDING DRESS WAS      "}
{"StartTime": "20101220234640.000", "EndTime": "20101220234640.000", "PrimaryTag": "CC1", "Text": "STILL VIVID.                    "}
{"StartTime": "20101220234640.000", "EndTime": "20101220234641.000", "PrimaryTag": "CC1", "Text": ">> TEARS STARTED RUNNING DOWN   "}
{"StartTime": "20101220234641.000", "EndTime": "20101220234642.000", "PrimaryTag": "CC1", "Text": "MY CHEEKS.                      "}
{"StartTime": "20101220234642.000", "EndTime": "20101220234643.000", "PrimaryTag": "CC1", "Text": ">> I DIDN'T THINK I WAS EVER    "}
{"StartTime": "20101220234643.000", "EndTime": "20101220234645.000", "PrimaryTag": "CC1", "Text": "GOING TO SEE THE DRESS AGAIN.   "}
{"StartTime": "20101220234645.000", "EndTime": "20101220234646.000", "PrimaryTag": "CC1", "Text": ">> THAT'S WHEN THE 25-YEAR-OLD  "}
{"StartTime": "20101220234646.000", "EndTime": "20101220234651.000", "PrimaryTag": "CC1", "Text": "BECAME A REAL LIFE NANCY DREW.  "}
{"StartTime": "20101220234651.000", "EndTime": "20101220234653.000", "PrimaryTag": "CC1", "Text": ">> ALL I COULD THINK WAS I AM   "}
{"StartTime": "20101220234653.000", "EndTime": "20101220234654.000", "PrimaryTag": "CC1", "Text": "GOING TO CATCH THE LITTLE PUNKS "}
{"StartTime": "20101220234654.000", "EndTime": "20101220234655.000", "PrimaryTag": "CC1", "Text": "THAT DID THIS.                  "}
{"StartTime": "20101220234655.000", "EndTime": "20101220234657.000", "PrimaryTag": "CC1", "Text": ">> A GUT FEELING LED HER TO     "}
{"StartTime": "20101220234657.000", "EndTime": "20101220234658.000", "PrimaryTag": "CC1", "Text": "SEARCH CRAIGSLIST HOPING THAT   "}
{"StartTime": "20101220234658.000", "EndTime": "20101220234701.000", "PrimaryTag": "CC1", "Text": "WHOEVER STOLE HER WEDDING DRESS "}
{"StartTime": "20101220234701.000", "EndTime": "20101220234702.000", "PrimaryTag": "CC1", "Text": "MIGHT TRY TO SELL IT.           "}
{"StartTime": "20101220234702.000", "EndTime": "20101220234703.000", "PrimaryTag": "CC1", "Text": "SHE POURED THROUGH COUNTLESS    "}
{"StartTime": "20101220234703.000", "EndTime": "20101220234707.000", "PrimaryTag": "CC1", "Text": "POSTINGS THEN SPOTTED ONE THAT  "}
{"StartTime": "20101220234707.000", "EndTime": "20101220234708.000", "PrimaryTag": "CC1", "Text": "READ DAVID'S BRIDAL DRESS.      "}
{"StartTime": "20101220234708.000", "EndTime": "20101220234711.000", "PrimaryTag": "CC1", "Text": "THAT'S WHERE SHE BOUGHT HER     "}
{"StartTime": "20101220234711.000", "EndTime": "20101220234712.000", "PrimaryTag": "CC1", "Text": "DRESS.                          "}
{"StartTime": "20101220234712.000", "EndTime": "20101220234713.000", "PrimaryTag": "CC1", "Text": ">> SAME SIZE.                   "}
{"StartTime": "20101220234713.000", "EndTime": "20101220234713.000", "PrimaryTag": "CC1", "Text": "SIZE 12.                        "}
{"StartTime": "20101220234713.000", "EndTime": "20101220234716.000", "PrimaryTag": "CC1", "Text": ">>  Deborah: SHE STARTED        "}
{"StartTime": "20101220234716.000", "EndTime": "20101220234717.000", "PrimaryTag": "CC1", "Text": "NEGOTIATING WITH A WOMAN CALLED "}
{"StartTime": "20101220234717.000", "EndTime": "20101220234717.000", "PrimaryTag": "CC1", "Text": "ASHLEY.                         "}
{"StartTime": "20101220234717.000", "EndTime": "20101220234719.000", "PrimaryTag": "CC1", "Text": ">> PLAIN WHITE AND BLACK SASH   "}
{"StartTime": "20101220234719.000", "EndTime": "20101220234720.000", "PrimaryTag": "CC1", "Text": "AND WHITE VEIL.                 "}
{"StartTime": "20101220234720.000", "EndTime": "20101220234721.000", "PrimaryTag": "CC1", "Text": ">>  Deborah: THEN CAME THIS     "}
{"StartTime": "20101220234721.000", "EndTime": "20101220234723.000", "PrimaryTag": "CC1", "Text": "TEXT FROM THE SELLER.           "}
{"StartTime": "20101220234723.000", "EndTime": "20101220234726.000", "PrimaryTag": "CC1", "Text": ">> ARE YOU WILLING TO PAY FULL  "}
{"StartTime": "20101220234726.000", "EndTime": "20101220234726.000", "PrimaryTag": "CC1", "Text": "PRICE?                          "}
{"StartTime": "20101220234726.000", "EndTime": "20101220234727.000", "PrimaryTag": "CC1", "Text": "ELAINA SET UP A STING AND SAID  "}
{"StartTime": "20101220234727.000", "EndTime": "20101220234729.000", "PrimaryTag": "CC1", "Text": "SHE ARRANGED TO MEET THE THIEF  "}
{"StartTime": "20101220234729.000", "EndTime": "20101220234732.000", "PrimaryTag": "CC1", "Text": "AT A SHOPPING MALL PARKING LOT. "}
{"StartTime": "20101220234732.000", "EndTime": "20101220234735.000", "PrimaryTag": "CC1", "Text": ">> I DIDN'T KNOW IF THEY HAD    "}
{"StartTime": "20101220234735.000", "EndTime": "20101220234735.000", "PrimaryTag": "CC1", "Text": "GUNS.                           "}
{"StartTime": "20101220234735.000", "EndTime": "20101220234736.000", "PrimaryTag": "CC1", "Text": ">> SHE GAVE THE CHIPPEWA FALLS  "}
{"StartTime": "20101220234736.000", "EndTime": "20101220234738.000", "PrimaryTag": "CC1", "Text": "PD THE LOCATION SO SHE HAD BACK "}
{"StartTime": "20101220234738.000", "EndTime": "20101220234738.000", "PrimaryTag": "CC1", "Text": "UP.                             "}
{"StartTime": "20101220234738.000", "EndTime": "20101220234739.000", "PrimaryTag": "CC1", "Text": ">> WE TRIED TO CONVINCE HER     "}
{"StartTime": "20101220234739.000", "EndTime": "20101220234742.000", "PrimaryTag": "CC1", "Text": "THAT SHE SHOULD NOT TAKE THIS   "}
{"StartTime": "20101220234742.000", "EndTime": "20101220234744.000", "PrimaryTag": "CC1", "Text": "INTO HER OWN HANDS AND NOTHING  "}
{"StartTime": "20101220234744.000", "EndTime": "20101220234745.000", "PrimaryTag": "CC1", "Text": "DOING, SHE WAS GOING TO GO MEET "}
{"StartTime": "20101220234745.000", "EndTime": "20101220234747.000", "PrimaryTag": "CC1", "Text": "THESE PEOPLE AND GET THE DRESS  "}
{"StartTime": "20101220234747.000", "EndTime": "20101220234747.000", "PrimaryTag": "CC1", "Text": "BACK.                           "}
{"StartTime": "20101220234747.000", "EndTime": "20101220234751.000", "PrimaryTag": "CC1", "Text": ">> JUST AS ELAINA PULLED IN THE "}
{"StartTime": "20101220234751.000", "EndTime": "20101220234753.000", "PrimaryTag": "CC1", "Text": "COPS MADE THEIR MOVE.           "}
{"StartTime": "20101220234753.000", "EndTime": "20101220234754.000", "PrimaryTag": "CC1", "Text": "THE CASE OF THE STOLEN WEDDING  "}
{"StartTime": "20101220234754.000", "EndTime": "20101220234755.000", "PrimaryTag": "CC1", "Text": "DRESS WAS SOLVED.               "}
{"StartTime": "20101220234755.000", "EndTime": "20101220234757.000", "PrimaryTag": "CC1", "Text": ">> THAT'S MY DRESS.             "}
{"StartTime": "20101220234757.000", "EndTime": "20101220234759.000", "PrimaryTag": "CC1", "Text": ">> POLICE ARRESTED 23-YEAR-OLD  "}
{"StartTime": "20101220234759.000", "EndTime": "20101220234800.000", "PrimaryTag": "CC1", "Text": "CHRISTOPHER ANDERSON AND TWO    "}
{"StartTime": "20101220234800.000", "EndTime": "20101220234800.000", "PrimaryTag": "CC1", "Text": "MINORS.                         "}
{"StartTime": "20101220234800.000", "EndTime": "20101220234801.000", "PrimaryTag": "CC1", "Text": "ELAINA SAYS FROM NOW ON SHE     "}
{"StartTime": "20101220234801.000", "EndTime": "20101220234804.000", "PrimaryTag": "CC1", "Text": "WILL KEEP A CLOSE EYE ON HER    "}
{"StartTime": "20101220234804.000", "EndTime": "20101220234805.000", "PrimaryTag": "CC1", "Text": "WEDDING DRESS.                  "}
{"StartTime": "20101220234805.000", "EndTime": "20101220234808.000", "PrimaryTag": "CC1", "Text": ">> KEEP THAT DRESS RIGHT NEXT   "}
{"StartTime": "20101220234808.000", "EndTime": "20101220234808.000", "PrimaryTag": "CC1", "Text": "TO MY BED.                      "}
{"StartTime": "20101220234808.000", "EndTime": "20101220234810.000", "PrimaryTag": "CC1", "Text": ">>  Deborah: THE ALLEGED THIEF  "}
{"StartTime": "20101220234810.000", "EndTime": "20101220234812.000", "PrimaryTag": "CC1", "Text": "FACES A MAXIMUM SENTENCE OF     "}
{"StartTime": "20101220234812.000", "EndTime": "20101220234814.000", "PrimaryTag": "CC1", "Text": "FOUR YEARS IN JAIL IF CONVICTED "}
{"StartTime": "20101220234814.000", "EndTime": "20101220234815.000", "PrimaryTag": "CC1", "Text": "AND A $10,000 FINE.             "}
{"StartTime": "20101220234815.000", "EndTime": "20101220234821.000", "PrimaryTag": "CC1", "Text": "ALL OF US FACE CHALLENGES BUT   "}
{"StartTime": "20101220234821.000", "EndTime": "20101220234827.000", "PrimaryTag": "CC1", "Text": "MOST OF THEM PEAL IN COMPARISON "}
{"StartTime": "20101220234827.000", "EndTime": "20101220234830.000", "PrimaryTag": "CC1", "Text": "PALE IN COMPARISON TO WHAT THIS "}
{"StartTime": "20101220234830.000", "EndTime": "20101220234831.000", "PrimaryTag": "CC1", "Text": "LITTLE BOY GOES THERE.          "}
{"StartTime": "20101220234831.000", "EndTime": "20101220234835.000", "PrimaryTag": "CC1", "Text": "A MOM WRAPS UP HER SON JUST     "}
{"StartTime": "20101220234835.000", "EndTime": "20101220234836.000", "PrimaryTag": "CC1", "Text": "LIKE A MUMMY CAREFULLY WRAPPING "}
{"StartTime": "20101220234836.000", "EndTime": "20101220234838.000", "PrimaryTag": "CC1", "Text": "THE BANDAGES ROUND AND ROUND    "}
{"StartTime": "20101220234838.000", "EndTime": "20101220234842.000", "PrimaryTag": "CC1", "Text": "MAKING SURE EVERY INCH OF HER   "}
{"StartTime": "20101220234842.000", "EndTime": "20101220234848.000", "PrimaryTag": "CC1", "Text": "SON'S BODY FROM HEAD-TO-TOE IS  "}
{"StartTime": "20101220234848.000", "EndTime": "20101220234849.000", "PrimaryTag": "CC1", "Text": "COMPLETELY COVERED.             "}
{"StartTime": "20101220234849.000", "EndTime": "20101220234850.000", "PrimaryTag": "CC1", "Text": "SO WHY THIS DAILY RITUAL?       "}
{"StartTime": "20101220234850.000", "EndTime": "20101220234851.000", "PrimaryTag": "CC1", "Text": "THIS 7-YEAR-OLD SUFFERS FROM A  "}
{"StartTime": "20101220234851.000", "EndTime": "20101220234853.000", "PrimaryTag": "CC1", "Text": "RARE SKIN DISEASE THAT CAUSES   "}
{"StartTime": "20101220234853.000", "EndTime": "20101220234854.000", "PrimaryTag": "CC1", "Text": "HIS SKIN TO EASILY BLISTER AND  "}
{"StartTime": "20101220234854.000", "EndTime": "20101220234855.000", "PrimaryTag": "CC1", "Text": "FALL OFF.                       "}
{"StartTime": "20101220234855.000", "EndTime": "20101220234856.000", "PrimaryTag": "CC1", "Text": "HE HAS BEEN CALLED THE BUTTER   "}
{"StartTime": "20101220234856.000", "EndTime": "20101220234900.000", "PrimaryTag": "CC1", "Text": "FLY BOY BECAUSE HIS SKIN CAN    "}
{"StartTime": "20101220234900.000", "EndTime": "20101220234903.000", "PrimaryTag": "CC1", "Text": "RIP JUST LIKE A BUTTER FLY'S    "}
{"StartTime": "20101220234903.000", "EndTime": "20101220234904.000", "PrimaryTag": "CC1", "Text": "WINGS.                          "}
{"StartTime": "20101220234904.000", "EndTime": "20101220234905.000", "PrimaryTag": "CC1", "Text": ">> YOU HAVE TO BE REALLY        "}
{"StartTime": "20101220234905.000", "EndTime": "20101220234907.000", "PrimaryTag": "CC1", "Text": "CAREFUL AROUND ME BECAUSE I     "}
{"StartTime": "20101220234907.000", "EndTime": "20101220234909.000", "PrimaryTag": "CC1", "Text": "HAVE FRAGILE SKIN.              "}
{"StartTime": "20101220234909.000", "EndTime": "20101220234912.000", "PrimaryTag": "CC1", "Text": ">> HIS MORNING STARTS BEFORE    "}
{"StartTime": "20101220234912.000", "EndTime": "20101220234914.000", "PrimaryTag": "CC1", "Text": "SUNRISE WITH A BIKE RIDE.       "}
{"StartTime": "20101220234914.000", "EndTime": "20101220234916.000", "PrimaryTag": "CC1", "Text": "THE SUN'S HEAT CAUSES BLISTERS. "}
{"StartTime": "20101220234916.000", "EndTime": "20101220234917.000", "PrimaryTag": "CC1", "Text": ">> EVEN PEDALING WILL CAUSE     "}
{"StartTime": "20101220234917.000", "EndTime": "20101220234919.000", "PrimaryTag": "CC1", "Text": "BLISTERS ON THE BOTTOM OF HIS   "}
{"StartTime": "20101220234919.000", "EndTime": "20101220234919.000", "PrimaryTag": "CC1", "Text": "FEET.                           "}
{"StartTime": "20101220234919.000", "EndTime": "20101220234920.000", "PrimaryTag": "CC1", "Text": "BUT HE IS A LITTLE BOY AND      "}
{"StartTime": "20101220234920.000", "EndTime": "20101220234922.000", "PrimaryTag": "CC1", "Text": "WANTS TO GET OUT AND DO THINGS  "}
{"StartTime": "20101220234922.000", "EndTime": "20101220234923.000", "PrimaryTag": "CC1", "Text": "LITTLE BOYS WANT TO DO.         "}
{"StartTime": "20101220234923.000", "EndTime": "20101220234925.000", "PrimaryTag": "CC1", "Text": ">> NOW HE IS OFF FOR A QUICK    "}
{"StartTime": "20101220234925.000", "EndTime": "20101220234928.000", "PrimaryTag": "CC1", "Text": "GAME OF HIDE AND GO SEEK.       "}
{"StartTime": "20101220234928.000", "EndTime": "20101220234928.000", "PrimaryTag": "CC1", "Text": "EVEN HIS INNOCENT CHILDHOOD     "}
{"StartTime": "20101220234928.000", "EndTime": "20101220234931.000", "PrimaryTag": "CC1", "Text": "ACTIVITY MUST ALSO BE LIMITED.  "}
{"StartTime": "20101220234931.000", "EndTime": "20101220234932.000", "PrimaryTag": "CC1", "Text": ">> IT IS ABOUT 8:30 A.M.        "}
{"StartTime": "20101220234932.000", "EndTime": "20101220234934.000", "PrimaryTag": "CC1", "Text": "AND IT IS ALREADY TOO HOT FOR   "}
{"StartTime": "20101220234934.000", "EndTime": "20101220234935.000", "PrimaryTag": "CC1", "Text": "HIM.                            "}
{"StartTime": "20101220234935.000", "EndTime": "20101220234937.000", "PrimaryTag": "CC1", "Text": ">> ZACH HEADS DIRECTLY TO HIS   "}
{"StartTime": "20101220234937.000", "EndTime": "20101220234938.000", "PrimaryTag": "CC1", "Text": "HOME'S AIR-CONDITIONING VENT    "}
{"StartTime": "20101220234938.000", "EndTime": "20101220234938.000", "PrimaryTag": "CC1", "Text": "FOR IMMEDIATE RELIEF.           "}
{"StartTime": "20101220234938.000", "EndTime": "20101220234941.000", "PrimaryTag": "CC1", "Text": "HIS LEAST FAVORITE PART OF THE  "}
{"StartTime": "20101220234941.000", "EndTime": "20101220234945.000", "PrimaryTag": "CC1", "Text": "DAY COMES WHEN HIS BANDAGES ARE "}
{"StartTime": "20101220234945.000", "EndTime": "20101220234947.000", "PrimaryTag": "CC1", "Text": "CHANGED AND HIS MOM STRETCHES   "}
{"StartTime": "20101220234947.000", "EndTime": "20101220234950.000", "PrimaryTag": "CC1", "Text": "HIS SCARED JOINTS TO KEEP THEM  "}
{"StartTime": "20101220234950.000", "EndTime": "20101220234950.000", "PrimaryTag": "CC1", "Text": "LIMBER.                         "}
{"StartTime": "20101220234950.000", "EndTime": "20101220234951.000", "PrimaryTag": "CC1", "Text": "BUT ZACH NEVER COMPLAINS.       "}
{"StartTime": "20101220234951.000", "EndTime": "20101220234952.000", "PrimaryTag": "CC1", "Text": "AS HE BRAVELY FACES SPENDING    "}
{"StartTime": "20101220234952.000", "EndTime": "20101220234955.000", "PrimaryTag": "CC1", "Text": "MUCH OF HIS YOUNG LIFE BEING    "}
{"StartTime": "20101220234955.000", "EndTime": "20101220234957.000", "PrimaryTag": "CC1", "Text": "WRAPPED LIKE A MUMMY.           "}
{"StartTime": "20101220234957.000", "EndTime": "20101220235001.000", "PrimaryTag": "CC1", "Text": ">> ZACH AS A PERSON ISN'T       "}
{"StartTime": "20101220235001.000", "EndTime": "20101220235001.000", "PrimaryTag": "CC1", "Text": "FRAGILE.                        "}
{"StartTime": "20101220235001.000", "EndTime": "20101220235002.000", "PrimaryTag": "CC1", "Text": "HE IS INCREDIBLY STRONG.        "}
{"StartTime": "20101220235002.000", "EndTime": "20101220235003.000", "PrimaryTag": "CC1", "Text": "HE IS AMAZING.                  "}
{"StartTime": "20101220235003.000", "EndTime": "20101220235006.000", "PrimaryTag": "CC1", "Text": ">> WE WILL BE BACK RIGHT AFTER  "}
{"StartTime": "20101220235006.000", "EndTime": "20101220235006.000", "PrimaryTag": "CC1", "Text": "THIS.                           "}
{"StartTime": "20101220235006.000", "EndTime": "20101220235007.000", "PrimaryTag": "CC1", "Text": ">> STILL TO COME, MIRROR,       "}
{"StartTime": "20101220235007.000", "EndTime": "20101220235009.000", "PrimaryTag": "CC1", "Text": "MIRROR ON THE WALL, WHO ARE THE "}
{"StartTime": "20101220235009.000", "EndTime": "20101220235010.000", "PrimaryTag": "CC1", "Text": "BEST DRESSED STARS OF THEM ALL. "}
{"StartTime": "20101220235010.000", "EndTime": "20101220235013.000", "PrimaryTag": "CC1", "Text": "WE WILL TELL YOU WHO LIT UP THE "}
{"StartTime": "20101220235013.000", "EndTime": "20101220235014.000", "PrimaryTag": "CC1", "Text": "RED CARPET IN 2010.             "}
{"StartTime": "20101220235014.000", "EndTime": "20101220235015.000", "PrimaryTag": "CC1", "Text": ">> PLUS, CATCH ME IF YOU CAN.   "}
{"StartTime": "20101220235015.000", "EndTime": "20101220235022.000", "PrimaryTag": "CC1", "Text": "IT IS A HIGH FLYING GET AWAY.   "}
{"StartTime": "20101220235022.000", "EndTime": "20101220235023.000", "PrimaryTag": "CC1", "Text": ">> CLOSED-CAPTIONING            "}
{"StartTime": "20101220235023.000", "EndTime": "20101220235023.000", "PrimaryTag": "CC1", "Text": "SPONSORSHIP FOR \"INSIDE         "}
{"StartTime": "20101220235023.000", "EndTime": "20101220235311.000", "PrimaryTag": "CC1", "Text": "EDITION\" IS BROUGHT TO YOU BY..."}
{"StartTime": "20101220235311.000", "EndTime": "20101220235313.000", "PrimaryTag": "CC1", "Text": ">> THEY ARE THE WOMEN THAT MADE "}
{"StartTime": "20101220235313.000", "EndTime": "20101220235314.000", "PrimaryTag": "CC1", "Text": "WATCHING RED CARPET ARRIVALS    "}
{"StartTime": "20101220235314.000", "EndTime": "20101220235315.000", "PrimaryTag": "CC1", "Text": "FUN.                            "}
{"StartTime": "20101220235315.000", "EndTime": "20101220235317.000", "PrimaryTag": "CC1", "Text": "HERE ARE OUR PICKS FOR BEST     "}
{"StartTime": "20101220235317.000", "EndTime": "20101220235318.000", "PrimaryTag": "CC1", "Text": "DRESSED IN 2010.                "}
{"StartTime": "20101220235318.000", "EndTime": "20101220235320.000", "PrimaryTag": "CC1", "Text": ">> 2010 WAS A YEAR OF FABULOUS  "}
{"StartTime": "20101220235320.000", "EndTime": "20101220235325.000", "PrimaryTag": "CC1", "Text": "FASHION ON THE RED CARPET.      "}
{"StartTime": "20101220235325.000", "EndTime": "20101220235326.000", "PrimaryTag": "CC1", "Text": "YOUNG HOLLYWOOD DRESSED TO      "}
{"StartTime": "20101220235326.000", "EndTime": "20101220235326.000", "PrimaryTag": "CC1", "Text": "IMPRESS.                        "}
{"StartTime": "20101220235326.000", "EndTime": "20101220235333.000", "PrimaryTag": "CC1", "Text": "LEAH MICHELE ALWAYS LOOKING     "}
{"StartTime": "20101220235333.000", "EndTime": "20101220235334.000", "PrimaryTag": "CC1", "Text": "BEAUTIFUL.                      "}
{"StartTime": "20101220235334.000", "EndTime": "20101220235334.000", "PrimaryTag": "CC1", "Text": "CHECK HER OUT AT THE EMMIES.    "}
{"StartTime": "20101220235334.000", "EndTime": "20101220235335.000", "PrimaryTag": "CC1", "Text": "RADIANT.                        "}
{"StartTime": "20101220235335.000", "EndTime": "20101220235338.000", "PrimaryTag": "CC1", "Text": "TAYLOR SWIFT GLIMMERED IN A     "}
{"StartTime": "20101220235338.000", "EndTime": "20101220235340.000", "PrimaryTag": "CC1", "Text": "MIDNIGHT BLUE FLOOR LENGTH GOWN "}
{"StartTime": "20101220235340.000", "EndTime": "20101220235342.000", "PrimaryTag": "CC1", "Text": "AT THE GRAMMIES AND MILEY CYRUS "}
{"StartTime": "20101220235342.000", "EndTime": "20101220235344.000", "PrimaryTag": "CC1", "Text": "HAD UPS AND DOWNS THIS YEAR BUT "}
{"StartTime": "20101220235344.000", "EndTime": "20101220235346.000", "PrimaryTag": "CC1", "Text": "HER STYLE HIT THE RIGHT NOTE.   "}
{"StartTime": "20101220235346.000", "EndTime": "20101220235351.000", "PrimaryTag": "CC1", "Text": "SHE LOOKED ALL GROWN UP AT THE  "}
{"StartTime": "20101220235351.000", "EndTime": "20101220235352.000", "PrimaryTag": "CC1", "Text": "OSCARS AND ANGELINA JOLIE       "}
{"StartTime": "20101220235352.000", "EndTime": "20101220235354.000", "PrimaryTag": "CC1", "Text": "CONTINUED AS A FASHION QUEEN.   "}
{"StartTime": "20101220235354.000", "EndTime": "20101220235355.000", "PrimaryTag": "CC1", "Text": "SHE LOOKED HOT, HOT, HOT AT THE "}
{"StartTime": "20101220235355.000", "EndTime": "20101220235357.000", "PrimaryTag": "CC1", "Text": "PREMIER OF HER MOVIE THE        "}
{"StartTime": "20101220235357.000", "EndTime": "20101220235358.000", "PrimaryTag": "CC1", "Text": "TOURIST.                        "}
{"StartTime": "20101220235358.000", "EndTime": "20101220235359.000", "PrimaryTag": "CC1", "Text": "AND ANGELINA JOLIE WASN'T THE   "}
{"StartTime": "20101220235359.000", "EndTime": "20101220235401.000", "PrimaryTag": "CC1", "Text": "ONLY SEXY MOM IN 2010.          "}
{"StartTime": "20101220235401.000", "EndTime": "20101220235402.000", "PrimaryTag": "CC1", "Text": "CHECK OUT HALLE BARRY.          "}
{"StartTime": "20101220235402.000", "EndTime": "20101220235404.000", "PrimaryTag": "CC1", "Text": "SIZZLING IN A RETRO LOOKING     "}
{"StartTime": "20101220235404.000", "EndTime": "20101220235405.000", "PrimaryTag": "CC1", "Text": "GOLDEN BLACK PANT SUIT AND      "}
{"StartTime": "20101220235405.000", "EndTime": "20101220235408.000", "PrimaryTag": "CC1", "Text": "SANDRA BULLOCK LOOKING LIKE A   "}
{"StartTime": "20101220235408.000", "EndTime": "20101220235412.000", "PrimaryTag": "CC1", "Text": "REAL LIFE OSCAR IN HER STUNNING "}
{"StartTime": "20101220235412.000", "EndTime": "20101220235414.000", "PrimaryTag": "CC1", "Text": "GOLD GOWN.                      "}
{"StartTime": "20101220235414.000", "EndTime": "20101220235416.000", "PrimaryTag": "CC1", "Text": "KATE HUDSON ALSO SHOWS THE      "}
{"StartTime": "20101220235416.000", "EndTime": "20101220235420.000", "PrimaryTag": "CC1", "Text": "DESIGNER AT THE GOLDEN GLOBE    "}
{"StartTime": "20101220235420.000", "EndTime": "20101220235421.000", "PrimaryTag": "CC1", "Text": "LOOKING STUNG.                  "}
{"StartTime": "20101220235421.000", "EndTime": "20101220235422.000", "PrimaryTag": "CC1", "Text": "DREW BARRYMORE RIGHT BEHIND     "}
{"StartTime": "20101220235422.000", "EndTime": "20101220235422.000", "PrimaryTag": "CC1", "Text": "HER.                            "}
{"StartTime": "20101220235422.000", "EndTime": "20101220235425.000", "PrimaryTag": "CC1", "Text": "RIGHT THERE WITH THE BLOND      "}
{"StartTime": "20101220235425.000", "EndTime": "20101220235429.000", "PrimaryTag": "CC1", "Text": "BEAUTY, MODERN FAMILY STAR      "}
{"StartTime": "20101220235429.000", "EndTime": "20101220235432.000", "PrimaryTag": "CC1", "Text": "GROWING IN A BEADED GOWN AT THE "}
{"StartTime": "20101220235432.000", "EndTime": "20101220235432.000", "PrimaryTag": "CC1", "Text": "EMMIES.                         "}
{"StartTime": "20101220235432.000", "EndTime": "20101220235434.000", "PrimaryTag": "CC1", "Text": "SPARKLE, SHINE AND LOTS OF SKIN "}
{"StartTime": "20101220235434.000", "EndTime": "20101220235435.000", "PrimaryTag": "CC1", "Text": "SIZZLED THE RED CARPETS THIS    "}
{"StartTime": "20101220235435.000", "EndTime": "20101220235435.000", "PrimaryTag": "CC1", "Text": "YEAR.                           "}
{"StartTime": "20101220235435.000", "EndTime": "20101220235437.000", "PrimaryTag": "CC1", "Text": ">> WHEN WE COME BACK, ONE OF    "}
{"StartTime": "20101220235437.000", "EndTime": "20101220235439.000", "PrimaryTag": "CC1", "Text": "THE MOST CREATIVE ESCAPES FROM  "}
{"StartTime": "20101220235439.000", "EndTime": "20101220235441.000", "PrimaryTag": "CC1", "Text": "THE LAW WE HAVE EVER SEEN.      "}
{"StartTime": "20101220235441.000", "EndTime": "20101220235713.000", "PrimaryTag": "CC1", "Text": "JUMPING OFF A BRIDGE.           "}
{"StartTime": "20101220235713.000", "EndTime": "20101220235904.000", "PrimaryTag": "CC1", "Text": "                      ????????? "}
{"StartTime": "20101220235904.000", "EndTime": "20101220235906.000", "PrimaryTag": "CC1", "Text": ">>  Deborah: FINALLY, A QUICK   "}
{"StartTime": "20101220235906.000", "EndTime": "20101220235909.000", "PrimaryTag": "CC1", "Text": "GET AWAY AS COPS MOVE IN.       "}
{"StartTime": "20101220235909.000", "EndTime": "20101220235914.000", "PrimaryTag": "CC1", "Text": ">> A CALIFORNIA FACE JUMPER     "}
{"StartTime": "20101220235914.000", "EndTime": "20101220235916.000", "PrimaryTag": "CC1", "Text": "PREPARES TO JUMP OFF A BRIDGE.  "}
{"StartTime": "20101220235916.000", "EndTime": "20101220235918.000", "PrimaryTag": "CC1", "Text": ">> DON'T EVEN THINK ABOUT IT.   "}
{"StartTime": "20101220235918.000", "EndTime": "20101220235925.000", "PrimaryTag": "CC1", "Text": ">> POLICE ARRIVE BUT STEVE      "}
{"StartTime": "20101220235925.000", "EndTime": "20101220235926.000", "PrimaryTag": "CC1", "Text": "JESTER ISN'T DETERRED.          "}
{"StartTime": "20101220235926.000", "EndTime": "20101220235930.000", "PrimaryTag": "CC1", "Text": "HE DOES A SUMMERSAULT OVER THE  "}
{"StartTime": "20101220235930.000", "EndTime": "20101220235930.000", "PrimaryTag": "CC1", "Text": "BRIDGE.                         "}
{"End": "20101220235930", "FileName": "2010-12-20_2330_US_KCAL_Inside_Edition"}
